{"meta":{"id":"aggregate__MLP__N3_IMAGE_NLP__w_equal","method":"aggregate","model":"MLP","scenario":"N3_IMAGE_NLP","scenario_label":"Image + NLP","scenario_series":"N","aggregation_weight":"w_equal","supported_regions":["Bangkalan","Gresik","Surabaya"],"supports_kecamatan":true,"has_shap_kecamatan":false,"has_shap_kabupaten":false,"has_shap_global":true,"is_default":false,"is_production":false,"metrics":{"mae":0.79,"rmse":0.964,"r2":0.9731,"spearman":0.981,"mape":15.42},"metric_weight":"w_equal","label":"MLP N3_IMAGE_NLP"},"kecamatan":{"Bangkalan|Konang":{"gid_3":"IDN.11.1.10_1","name_2":"Bangkalan","name_3":"Konang","series":[{"year":2018,"prediction_dl_percent":8.902,"std":0.497},{"year":2019,"prediction_dl_percent":19.037,"std":0.137},{"year":2020,"prediction_dl_percent":19.105,"std":0.15},{"year":2021,"prediction_dl_percent":19.126,"std":0.133},{"year":2022,"prediction_dl_percent":19.093,"std":0.14},{"year":2023,"prediction_dl_percent":18.98,"std":0.151},{"year":2024,"prediction_dl_percent":19.004,"std":0.138},{"year":2025,"prediction_dl_percent":18.024,"std":0.453},{"year":2026,"prediction_dl_percent":17.044,"std":0.453,"prediction_type":"linear_projection_from_2024_2025"}]},"Bangkalan|Kwanyar":{"gid_3":"IDN.11.1.11_1","name_2":"Bangkalan","name_3":"Kwanyar","series":[{"year":2018,"prediction_dl_percent":18.964,"std":0.093},{"year":2019,"prediction_dl_percent":18.995,"std":0.112},{"year":2020,"prediction_dl_percent":19.072,"std":0.128},{"year":2021,"prediction_dl_percent":19.066,"std":0.114},{"year":2022,"prediction_dl_percent":19.038,"std":0.117},{"year":2023,"prediction_dl_percent":18.919,"std":0.162},{"year":2024,"prediction_dl_percent":18.922,"std":0.144},{"year":2025,"prediction_dl_percent":17.658,"std":0.459},{"year":2026,"prediction_dl_percent":16.394,"std":0.459,"prediction_type":"linear_projection_from_2024_2025"}]},"Bangkalan|Labang":{"gid_3":"IDN.11.1.12_1","name_2":"Bangkalan","name_3":"Labang","series":[{"year":2018,"prediction_dl_percent":18.874,"std":0.097},{"year":2019,"prediction_dl_percent":18.99,"std":0.131},{"year":2020,"prediction_dl_percent":19.069,"std":0.141},{"year":2021,"prediction_dl_percent":19.092,"std":0.115},{"year":2022,"prediction_dl_percent":19.048,"std":0.106},{"year":2023,"prediction_dl_percent":18.934,"std":0.147},{"year":2024,"prediction_dl_percent":18.923,"std":0.11},{"year":2025,"prediction_dl_percent":17.82,"std":0.482},{"year":2026,"prediction_dl_percent":16.717,"std":0.482,"prediction_type":"linear_projection_from_2024_2025"}]},"Bangkalan|Modung":{"gid_3":"IDN.11.1.13_1","name_2":"Bangkalan","name_3":"Modung","series":[{"year":2018,"prediction_dl_percent":8.902,"std":0.497},{"year":2019,"prediction_dl_percent":19.066,"std":0.152},{"year":2020,"prediction_dl_percent":19.116,"std":0.142},{"year":2021,"prediction_dl_percent":19.126,"std":0.134},{"year":2022,"prediction_dl_percent":19.087,"std":0.135},{"year":2023,"prediction_dl_percent":18.971,"std":0.157},{"year":2024,"prediction_dl_percent":18.985,"std":0.135},{"year":2025,"prediction_dl_percent":18.095,"std":0.387},{"year":2026,"prediction_dl_percent":17.205,"std":0.387,"prediction_type":"linear_projection_from_2024_2025"}]},"Bangkalan|Sepulu":{"gid_3":"IDN.11.1.14_1","name_2":"Bangkalan","name_3":"Sepulu","series":[{"year":2018,"prediction_dl_percent":8.902,"std":0.497},{"year":2019,"prediction_dl_percent":19.068,"std":0.152},{"year":2020,"prediction_dl_percent":19.093,"std":0.161},{"year":2021,"prediction_dl_percent":19.117,"std":0.138},{"year":2022,"prediction_dl_percent":19.092,"std":0.139},{"year":2023,"prediction_dl_percent":18.997,"std":0.151},{"year":2024,"prediction_dl_percent":18.993,"std":0.135},{"year":2025,"prediction_dl_percent":17.956,"std":0.49},{"year":2026,"prediction_dl_percent":16.919,"std":0.49,"prediction_type":"linear_projection_from_2024_2025"}]},"Bangkalan|Socah":{"gid_3":"IDN.11.1.15_1","name_2":"Bangkalan","name_3":"Socah","series":[{"year":2018,"prediction_dl_percent":18.914,"std":0.116},{"year":2019,"prediction_dl_percent":19.027,"std":0.145},{"year":2020,"prediction_dl_percent":19.086,"std":0.127},{"year":2021,"prediction_dl_percent":19.09,"std":0.113},{"year":2022,"prediction_dl_percent":19.06,"std":0.12},{"year":2023,"prediction_dl_percent":18.966,"std":0.171},{"year":2024,"prediction_dl_percent":18.95,"std":0.125},{"year":2025,"prediction_dl_percent":17.702,"std":0.609},{"year":2026,"prediction_dl_percent":16.454,"std":0.609,"prediction_type":"linear_projection_from_2024_2025"}]},"Bangkalan|TanahMerah":{"gid_3":"IDN.11.1.16_1","name_2":"Bangkalan","name_3":"TanahMerah","series":[{"year":2018,"prediction_dl_percent":18.949,"std":0.111},{"year":2019,"prediction_dl_percent":19.072,"std":0.147},{"year":2020,"prediction_dl_percent":19.12,"std":0.149},{"year":2021,"prediction_dl_percent":19.128,"std":0.133},{"year":2022,"prediction_dl_percent":19.099,"std":0.133},{"year":2023,"prediction_dl_percent":18.979,"std":0.153},{"year":2024,"prediction_dl_percent":18.998,"std":0.129},{"year":2025,"prediction_dl_percent":17.986,"std":0.46},{"year":2026,"prediction_dl_percent":16.974,"std":0.46,"prediction_type":"linear_projection_from_2024_2025"}]},"Bangkalan|Tanjungbumi":{"gid_3":"IDN.11.1.17_1","name_2":"Bangkalan","name_3":"Tanjungbumi","series":[{"year":2018,"prediction_dl_percent":8.902,"std":0.497},{"year":2019,"prediction_dl_percent":19.046,"std":0.143},{"year":2020,"prediction_dl_percent":19.084,"std":0.144},{"year":2021,"prediction_dl_percent":19.123,"std":0.141},{"year":2022,"prediction_dl_percent":19.086,"std":0.142},{"year":2023,"prediction_dl_percent":18.981,"std":0.166},{"year":2024,"prediction_dl_percent":18.992,"std":0.137},{"year":2025,"prediction_dl_percent":17.912,"std":0.452},{"year":2026,"prediction_dl_percent":16.832,"std":0.452,"prediction_type":"linear_projection_from_2024_2025"}]},"Bangkalan|Tragah":{"gid_3":"IDN.11.1.18_1","name_2":"Bangkalan","name_3":"Tragah","series":[{"year":2018,"prediction_dl_percent":18.986,"std":0.122},{"year":2019,"prediction_dl_percent":19.076,"std":0.148},{"year":2020,"prediction_dl_percent":19.126,"std":0.143},{"year":2021,"prediction_dl_percent":19.13,"std":0.134},{"year":2022,"prediction_dl_percent":19.099,"std":0.141},{"year":2023,"prediction_dl_percent":18.978,"std":0.159},{"year":2024,"prediction_dl_percent":18.99,"std":0.138},{"year":2025,"prediction_dl_percent":17.998,"std":0.484},{"year":2026,"prediction_dl_percent":17.006,"std":0.484,"prediction_type":"linear_projection_from_2024_2025"}]},"Bangkalan|Arosbaya":{"gid_3":"IDN.11.1.1_1","name_2":"Bangkalan","name_3":"Arosbaya","series":[{"year":2018,"prediction_dl_percent":18.925,"std":0.12},{"year":2019,"prediction_dl_percent":19.058,"std":0.154},{"year":2020,"prediction_dl_percent":19.114,"std":0.141},{"year":2021,"prediction_dl_percent":19.127,"std":0.136},{"year":2022,"prediction_dl_percent":19.095,"std":0.141},{"year":2023,"prediction_dl_percent":18.982,"std":0.172},{"year":2024,"prediction_dl_percent":18.984,"std":0.15},{"year":2025,"prediction_dl_percent":17.914,"std":0.524},{"year":2026,"prediction_dl_percent":16.844,"std":0.524,"prediction_type":"linear_projection_from_2024_2025"}]},"Bangkalan|Bangkalan":{"gid_3":"IDN.11.1.2_1","name_2":"Bangkalan","name_3":"Bangkalan","series":[{"year":2018,"prediction_dl_percent":18.845,"std":0.14},{"year":2019,"prediction_dl_percent":18.967,"std":0.142},{"year":2020,"prediction_dl_percent":19.031,"std":0.114},{"year":2021,"prediction_dl_percent":19.052,"std":0.114},{"year":2022,"prediction_dl_percent":18.986,"std":0.121},{"year":2023,"prediction_dl_percent":18.807,"std":0.151},{"year":2024,"prediction_dl_percent":18.777,"std":0.121},{"year":2025,"prediction_dl_percent":17.014,"std":0.658},{"year":2026,"prediction_dl_percent":15.251,"std":0.658,"prediction_type":"linear_projection_from_2024_2025"}]},"Bangkalan|Blega":{"gid_3":"IDN.11.1.3_1","name_2":"Bangkalan","name_3":"Blega","series":[{"year":2018,"prediction_dl_percent":8.902,"std":0.497},{"year":2019,"prediction_dl_percent":19.043,"std":0.135},{"year":2020,"prediction_dl_percent":19.116,"std":0.141},{"year":2021,"prediction_dl_percent":19.123,"std":0.131},{"year":2022,"prediction_dl_percent":19.089,"std":0.134},{"year":2023,"prediction_dl_percent":18.959,"std":0.164},{"year":2024,"prediction_dl_percent":18.987,"std":0.132},{"year":2025,"prediction_dl_percent":18.136,"std":0.413},{"year":2026,"prediction_dl_percent":17.285,"std":0.413,"prediction_type":"linear_projection_from_2024_2025"}]},"Bangkalan|Burneh":{"gid_3":"IDN.11.1.4_1","name_2":"Bangkalan","name_3":"Burneh","series":[{"year":2018,"prediction_dl_percent":18.871,"std":0.11},{"year":2019,"prediction_dl_percent":18.988,"std":0.131},{"year":2020,"prediction_dl_percent":19.08,"std":0.141},{"year":2021,"prediction_dl_percent":19.106,"std":0.133},{"year":2022,"prediction_dl_percent":19.071,"std":0.14},{"year":2023,"prediction_dl_percent":18.913,"std":0.181},{"year":2024,"prediction_dl_percent":18.94,"std":0.144},{"year":2025,"prediction_dl_percent":17.711,"std":0.586},{"year":2026,"prediction_dl_percent":16.482,"std":0.586,"prediction_type":"linear_projection_from_2024_2025"}]},"Bangkalan|Galis":{"gid_3":"IDN.11.1.5_1","name_2":"Bangkalan","name_3":"Galis","series":[{"year":2018,"prediction_dl_percent":8.902,"std":0.497},{"year":2019,"prediction_dl_percent":19.054,"std":0.139},{"year":2020,"prediction_dl_percent":19.123,"std":0.144},{"year":2021,"prediction_dl_percent":19.131,"std":0.131},{"year":2022,"prediction_dl_percent":19.101,"std":0.14},{"year":2023,"prediction_dl_percent":18.983,"std":0.165},{"year":2024,"prediction_dl_percent":19.002,"std":0.146},{"year":2025,"prediction_dl_percent":18.035,"std":0.469},{"year":2026,"prediction_dl_percent":17.068,"std":0.469,"prediction_type":"linear_projection_from_2024_2025"}]},"Bangkalan|Geger":{"gid_3":"IDN.11.1.6_1","name_2":"Bangkalan","name_3":"Geger","series":[{"year":2018,"prediction_dl_percent":18.963,"std":0.099},{"year":2019,"prediction_dl_percent":19.07,"std":0.146},{"year":2020,"prediction_dl_percent":19.121,"std":0.144},{"year":2021,"prediction_dl_percent":19.128,"std":0.132},{"year":2022,"prediction_dl_percent":19.099,"std":0.137},{"year":2023,"prediction_dl_percent":18.998,"std":0.173},{"year":2024,"prediction_dl_percent":19.002,"std":0.149},{"year":2025,"prediction_dl_percent":18.076,"std":0.428},{"year":2026,"prediction_dl_percent":17.15,"std":0.428,"prediction_type":"linear_projection_from_2024_2025"}]},"Bangkalan|Kamal":{"gid_3":"IDN.11.1.7_1","name_2":"Bangkalan","name_3":"Kamal","series":[{"year":2018,"prediction_dl_percent":18.901,"std":0.099},{"year":2019,"prediction_dl_percent":19.004,"std":0.138},{"year":2020,"prediction_dl_percent":19.091,"std":0.131},{"year":2021,"prediction_dl_percent":19.107,"std":0.132},{"year":2022,"prediction_dl_percent":19.07,"std":0.135},{"year":2023,"prediction_dl_percent":18.948,"std":0.173},{"year":2024,"prediction_dl_percent":18.949,"std":0.148},{"year":2025,"prediction_dl_percent":17.943,"std":0.366},{"year":2026,"prediction_dl_percent":16.937,"std":0.366,"prediction_type":"linear_projection_from_2024_2025"}]},"Bangkalan|Klampis":{"gid_3":"IDN.11.1.8_1","name_2":"Bangkalan","name_3":"Klampis","series":[{"year":2018,"prediction_dl_percent":18.86,"std":0.099},{"year":2019,"prediction_dl_percent":19.079,"std":0.154},{"year":2020,"prediction_dl_percent":19.121,"std":0.148},{"year":2021,"prediction_dl_percent":19.131,"std":0.137},{"year":2022,"prediction_dl_percent":19.091,"std":0.139},{"year":2023,"prediction_dl_percent":18.986,"std":0.164},{"year":2024,"prediction_dl_percent":18.997,"std":0.138},{"year":2025,"prediction_dl_percent":17.995,"std":0.407},{"year":2026,"prediction_dl_percent":16.993,"std":0.407,"prediction_type":"linear_projection_from_2024_2025"}]},"Bangkalan|Kokop":{"gid_3":"IDN.11.1.9_1","name_2":"Bangkalan","name_3":"Kokop","series":[{"year":2018,"prediction_dl_percent":8.902,"std":0.497},{"year":2019,"prediction_dl_percent":19.071,"std":0.143},{"year":2020,"prediction_dl_percent":19.107,"std":0.141},{"year":2021,"prediction_dl_percent":19.126,"std":0.135},{"year":2022,"prediction_dl_percent":19.095,"std":0.137},{"year":2023,"prediction_dl_percent":18.995,"std":0.165},{"year":2024,"prediction_dl_percent":19.007,"std":0.145},{"year":2025,"prediction_dl_percent":18.077,"std":0.43},{"year":2026,"prediction_dl_percent":17.147,"std":0.43,"prediction_type":"linear_projection_from_2024_2025"}]},"Surabaya|Jambangan":{"gid_3":"IDN.11.35.10_1","name_2":"Surabaya","name_3":"Jambangan","series":[{"year":2018,"prediction_dl_percent":8.647,"std":0.466},{"year":2019,"prediction_dl_percent":4.839,"std":0.157},{"year":2020,"prediction_dl_percent":4.339,"std":0.111},{"year":2021,"prediction_dl_percent":4.474,"std":0.135},{"year":2022,"prediction_dl_percent":4.396,"std":0.149},{"year":2023,"prediction_dl_percent":6.201,"std":0.68},{"year":2024,"prediction_dl_percent":6.23,"std":0.586},{"year":2025,"prediction_dl_percent":5.76,"std":0.52},{"year":2026,"prediction_dl_percent":5.29,"std":0.52,"prediction_type":"linear_projection_from_2024_2025"}]},"Surabaya|KarangPilang":{"gid_3":"IDN.11.35.11_1","name_2":"Surabaya","name_3":"KarangPilang","series":[{"year":2018,"prediction_dl_percent":3.847,"std":0.113},{"year":2019,"prediction_dl_percent":3.34,"std":0.104},{"year":2020,"prediction_dl_percent":3.357,"std":0.104},{"year":2021,"prediction_dl_percent":3.369,"std":0.015},{"year":2022,"prediction_dl_percent":3.469,"std":0.067},{"year":2023,"prediction_dl_percent":3.901,"std":0.186},{"year":2024,"prediction_dl_percent":3.991,"std":0.169},{"year":2025,"prediction_dl_percent":3.93,"std":0.121},{"year":2026,"prediction_dl_percent":3.869,"std":0.121,"prediction_type":"linear_projection_from_2024_2025"}]},"Surabaya|Kenjeran":{"gid_3":"IDN.11.35.12_1","name_2":"Surabaya","name_3":"Kenjeran","series":[{"year":2018,"prediction_dl_percent":8.647,"std":0.466},{"year":2019,"prediction_dl_percent":4.839,"std":0.157},{"year":2020,"prediction_dl_percent":4.339,"std":0.111},{"year":2021,"prediction_dl_percent":4.474,"std":0.135},{"year":2022,"prediction_dl_percent":4.396,"std":0.149},{"year":2023,"prediction_dl_percent":6.201,"std":0.68},{"year":2024,"prediction_dl_percent":6.23,"std":0.586},{"year":2025,"prediction_dl_percent":5.76,"std":0.52},{"year":2026,"prediction_dl_percent":5.29,"std":0.52,"prediction_type":"linear_projection_from_2024_2025"}]},"Surabaya|Krembangan":{"gid_3":"IDN.11.35.13_1","name_2":"Surabaya","name_3":"Krembangan","series":[{"year":2018,"prediction_dl_percent":8.647,"std":0.466},{"year":2019,"prediction_dl_percent":4.839,"std":0.157},{"year":2020,"prediction_dl_percent":4.339,"std":0.111},{"year":2021,"prediction_dl_percent":4.474,"std":0.135},{"year":2022,"prediction_dl_percent":4.396,"std":0.149},{"year":2023,"prediction_dl_percent":6.201,"std":0.68},{"year":2024,"prediction_dl_percent":6.23,"std":0.586},{"year":2025,"prediction_dl_percent":5.76,"std":0.52},{"year":2026,"prediction_dl_percent":5.29,"std":0.52,"prediction_type":"linear_projection_from_2024_2025"}]},"Surabaya|Lakarsantri":{"gid_3":"IDN.11.35.14_1","name_2":"Surabaya","name_3":"Lakarsantri","series":[{"year":2018,"prediction_dl_percent":4.854,"std":0.557},{"year":2019,"prediction_dl_percent":3.552,"std":0.218},{"year":2020,"prediction_dl_percent":3.585,"std":0.174},{"year":2021,"prediction_dl_percent":3.811,"std":0.145},{"year":2022,"prediction_dl_percent":4.074,"std":0.179},{"year":2023,"prediction_dl_percent":4.656,"std":0.429},{"year":2024,"prediction_dl_percent":4.817,"std":0.488},{"year":2025,"prediction_dl_percent":4.751,"std":0.502},{"year":2026,"prediction_dl_percent":4.685,"std":0.502,"prediction_type":"linear_projection_from_2024_2025"}]},"Surabaya|Mulyorejo":{"gid_3":"IDN.11.35.15_1","name_2":"Surabaya","name_3":"Mulyorejo","series":[{"year":2018,"prediction_dl_percent":8.647,"std":0.466},{"year":2019,"prediction_dl_percent":4.839,"std":0.157},{"year":2020,"prediction_dl_percent":4.339,"std":0.111},{"year":2021,"prediction_dl_percent":4.474,"std":0.135},{"year":2022,"prediction_dl_percent":4.396,"std":0.149},{"year":2023,"prediction_dl_percent":6.201,"std":0.68},{"year":2024,"prediction_dl_percent":6.23,"std":0.586},{"year":2025,"prediction_dl_percent":5.76,"std":0.52},{"year":2026,"prediction_dl_percent":5.29,"std":0.52,"prediction_type":"linear_projection_from_2024_2025"}]},"Surabaya|PabeanCantian":{"gid_3":"IDN.11.35.16_1","name_2":"Surabaya","name_3":"PabeanCantian","series":[{"year":2018,"prediction_dl_percent":8.647,"std":0.466},{"year":2019,"prediction_dl_percent":4.839,"std":0.157},{"year":2020,"prediction_dl_percent":4.339,"std":0.111},{"year":2021,"prediction_dl_percent":4.474,"std":0.135},{"year":2022,"prediction_dl_percent":4.396,"std":0.149},{"year":2023,"prediction_dl_percent":6.201,"std":0.68},{"year":2024,"prediction_dl_percent":6.23,"std":0.586},{"year":2025,"prediction_dl_percent":5.76,"std":0.52},{"year":2026,"prediction_dl_percent":5.29,"std":0.52,"prediction_type":"linear_projection_from_2024_2025"}]},"Surabaya|Pakal":{"gid_3":"IDN.11.35.17_1","name_2":"Surabaya","name_3":"Pakal","series":[{"year":2018,"prediction_dl_percent":13.762,"std":2.298},{"year":2019,"prediction_dl_percent":7.772,"std":2.204},{"year":2020,"prediction_dl_percent":7.73,"std":2.259},{"year":2021,"prediction_dl_percent":6.418,"std":1.418},{"year":2022,"prediction_dl_percent":9.1,"std":1.776},{"year":2023,"prediction_dl_percent":6.897,"std":1.155},{"year":2024,"prediction_dl_percent":8.444,"std":1.895},{"year":2025,"prediction_dl_percent":8.348,"std":1.758},{"year":2026,"prediction_dl_percent":8.252,"std":1.758,"prediction_type":"linear_projection_from_2024_2025"}]},"Surabaya|Rungkut":{"gid_3":"IDN.11.35.18_1","name_2":"Surabaya","name_3":"Rungkut","series":[{"year":2018,"prediction_dl_percent":4.614,"std":0.162},{"year":2019,"prediction_dl_percent":3.572,"std":0.075},{"year":2020,"prediction_dl_percent":3.559,"std":0.047},{"year":2021,"prediction_dl_percent":3.674,"std":0.119},{"year":2022,"prediction_dl_percent":4.197,"std":0.365},{"year":2023,"prediction_dl_percent":4.376,"std":0.358},{"year":2024,"prediction_dl_percent":4.576,"std":0.312},{"year":2025,"prediction_dl_percent":4.448,"std":0.282},{"year":2026,"prediction_dl_percent":4.32,"std":0.282,"prediction_type":"linear_projection_from_2024_2025"}]},"Surabaya|Sambikerep":{"gid_3":"IDN.11.35.19_1","name_2":"Surabaya","name_3":"Sambikerep","series":[{"year":2018,"prediction_dl_percent":4.958,"std":0.435},{"year":2019,"prediction_dl_percent":3.555,"std":0.165},{"year":2020,"prediction_dl_percent":3.731,"std":0.122},{"year":2021,"prediction_dl_percent":3.959,"std":0.179},{"year":2022,"prediction_dl_percent":4.201,"std":0.121},{"year":2023,"prediction_dl_percent":4.725,"std":0.077},{"year":2024,"prediction_dl_percent":4.85,"std":0.101},{"year":2025,"prediction_dl_percent":4.836,"std":0.14},{"year":2026,"prediction_dl_percent":4.822,"std":0.14,"prediction_type":"linear_projection_from_2024_2025"}]},"Surabaya|Asemrowo":{"gid_3":"IDN.11.35.1_1","name_2":"Surabaya","name_3":"Asemrowo","series":[{"year":2018,"prediction_dl_percent":3.83,"std":0.031},{"year":2019,"prediction_dl_percent":3.335,"std":0.062},{"year":2020,"prediction_dl_percent":3.375,"std":0.067},{"year":2021,"prediction_dl_percent":3.474,"std":0.038},{"year":2022,"prediction_dl_percent":3.574,"std":0.048},{"year":2023,"prediction_dl_percent":4.225,"std":0.237},{"year":2024,"prediction_dl_percent":4.31,"std":0.273},{"year":2025,"prediction_dl_percent":4.247,"std":0.205},{"year":2026,"prediction_dl_percent":4.184,"std":0.205,"prediction_type":"linear_projection_from_2024_2025"}]},"Surabaya|Sawahan":{"gid_3":"IDN.11.35.20_1","name_2":"Surabaya","name_3":"Sawahan","series":[{"year":2018,"prediction_dl_percent":8.647,"std":0.466},{"year":2019,"prediction_dl_percent":4.839,"std":0.157},{"year":2020,"prediction_dl_percent":4.339,"std":0.111},{"year":2021,"prediction_dl_percent":4.474,"std":0.135},{"year":2022,"prediction_dl_percent":4.396,"std":0.149},{"year":2023,"prediction_dl_percent":6.201,"std":0.68},{"year":2024,"prediction_dl_percent":6.23,"std":0.586},{"year":2025,"prediction_dl_percent":5.76,"std":0.52},{"year":2026,"prediction_dl_percent":5.29,"std":0.52,"prediction_type":"linear_projection_from_2024_2025"}]},"Surabaya|Semampir":{"gid_3":"IDN.11.35.21_1","name_2":"Surabaya","name_3":"Semampir","series":[{"year":2018,"prediction_dl_percent":4.311,"std":0.119},{"year":2019,"prediction_dl_percent":3.454,"std":0.126},{"year":2020,"prediction_dl_percent":3.564,"std":0.117},{"year":2021,"prediction_dl_percent":3.611,"std":0.151},{"year":2022,"prediction_dl_percent":3.728,"std":0.263},{"year":2023,"prediction_dl_percent":4.279,"std":0.439},{"year":2024,"prediction_dl_percent":4.452,"std":0.394},{"year":2025,"prediction_dl_percent":4.316,"std":0.328},{"year":2026,"prediction_dl_percent":4.18,"std":0.328,"prediction_type":"linear_projection_from_2024_2025"}]},"Surabaya|Simokerto":{"gid_3":"IDN.11.35.22_1","name_2":"Surabaya","name_3":"Simokerto","series":[{"year":2018,"prediction_dl_percent":8.647,"std":0.466},{"year":2019,"prediction_dl_percent":4.839,"std":0.157},{"year":2020,"prediction_dl_percent":4.339,"std":0.111},{"year":2021,"prediction_dl_percent":4.474,"std":0.135},{"year":2022,"prediction_dl_percent":4.396,"std":0.149},{"year":2023,"prediction_dl_percent":6.201,"std":0.68},{"year":2024,"prediction_dl_percent":6.23,"std":0.586},{"year":2025,"prediction_dl_percent":5.76,"std":0.52},{"year":2026,"prediction_dl_percent":5.29,"std":0.52,"prediction_type":"linear_projection_from_2024_2025"}]},"Surabaya|SukoManunggal":{"gid_3":"IDN.11.35.23_1","name_2":"Surabaya","name_3":"SukoManunggal","series":[{"year":2018,"prediction_dl_percent":8.647,"std":0.466},{"year":2019,"prediction_dl_percent":4.839,"std":0.157},{"year":2020,"prediction_dl_percent":4.339,"std":0.111},{"year":2021,"prediction_dl_percent":4.474,"std":0.135},{"year":2022,"prediction_dl_percent":4.396,"std":0.149},{"year":2023,"prediction_dl_percent":6.201,"std":0.68},{"year":2024,"prediction_dl_percent":6.23,"std":0.586},{"year":2025,"prediction_dl_percent":5.76,"std":0.52},{"year":2026,"prediction_dl_percent":5.29,"std":0.52,"prediction_type":"linear_projection_from_2024_2025"}]},"Surabaya|Sukolilo":{"gid_3":"IDN.11.35.24_1","name_2":"Surabaya","name_3":"Sukolilo","series":[{"year":2018,"prediction_dl_percent":4.3,"std":0.102},{"year":2019,"prediction_dl_percent":3.44,"std":0.063},{"year":2020,"prediction_dl_percent":3.475,"std":0.12},{"year":2021,"prediction_dl_percent":3.54,"std":0.144},{"year":2022,"prediction_dl_percent":3.64,"std":0.258},{"year":2023,"prediction_dl_percent":4.286,"std":0.498},{"year":2024,"prediction_dl_percent":4.44,"std":0.511},{"year":2025,"prediction_dl_percent":4.259,"std":0.52},{"year":2026,"prediction_dl_percent":4.078,"std":0.52,"prediction_type":"linear_projection_from_2024_2025"}]},"Surabaya|Tambaksari":{"gid_3":"IDN.11.35.25_1","name_2":"Surabaya","name_3":"Tambaksari","series":[{"year":2018,"prediction_dl_percent":3.842,"std":0.177},{"year":2019,"prediction_dl_percent":3.303,"std":0.054},{"year":2020,"prediction_dl_percent":3.404,"std":0.137},{"year":2021,"prediction_dl_percent":3.473,"std":0.095},{"year":2022,"prediction_dl_percent":3.541,"std":0.113},{"year":2023,"prediction_dl_percent":4.02,"std":0.346},{"year":2024,"prediction_dl_percent":4.169,"std":0.327},{"year":2025,"prediction_dl_percent":4.096,"std":0.262},{"year":2026,"prediction_dl_percent":4.023,"std":0.262,"prediction_type":"linear_projection_from_2024_2025"}]},"Surabaya|Tandes":{"gid_3":"IDN.11.35.26_1","name_2":"Surabaya","name_3":"Tandes","series":[{"year":2018,"prediction_dl_percent":4.073,"std":0.173},{"year":2019,"prediction_dl_percent":3.402,"std":0.067},{"year":2020,"prediction_dl_percent":3.518,"std":0.113},{"year":2021,"prediction_dl_percent":3.588,"std":0.105},{"year":2022,"prediction_dl_percent":3.644,"std":0.194},{"year":2023,"prediction_dl_percent":4.088,"std":0.381},{"year":2024,"prediction_dl_percent":4.315,"std":0.377},{"year":2025,"prediction_dl_percent":4.305,"std":0.246},{"year":2026,"prediction_dl_percent":4.295,"std":0.246,"prediction_type":"linear_projection_from_2024_2025"}]},"Surabaya|Tegalsari":{"gid_3":"IDN.11.35.27_1","name_2":"Surabaya","name_3":"Tegalsari","series":[{"year":2018,"prediction_dl_percent":3.588,"std":0.051},{"year":2019,"prediction_dl_percent":3.23,"std":0.057},{"year":2020,"prediction_dl_percent":3.282,"std":0.129},{"year":2021,"prediction_dl_percent":3.347,"std":0.114},{"year":2022,"prediction_dl_percent":3.382,"std":0.14},{"year":2023,"prediction_dl_percent":3.726,"std":0.387},{"year":2024,"prediction_dl_percent":3.836,"std":0.409},{"year":2025,"prediction_dl_percent":3.812,"std":0.302},{"year":2026,"prediction_dl_percent":3.788,"std":0.302,"prediction_type":"linear_projection_from_2024_2025"}]},"Surabaya|TenggilisMejoyo":{"gid_3":"IDN.11.35.28_1","name_2":"Surabaya","name_3":"TenggilisMejoyo","series":[{"year":2018,"prediction_dl_percent":8.647,"std":0.466},{"year":2019,"prediction_dl_percent":4.839,"std":0.157},{"year":2020,"prediction_dl_percent":4.339,"std":0.111},{"year":2021,"prediction_dl_percent":4.474,"std":0.135},{"year":2022,"prediction_dl_percent":4.396,"std":0.149},{"year":2023,"prediction_dl_percent":6.201,"std":0.68},{"year":2024,"prediction_dl_percent":6.23,"std":0.586},{"year":2025,"prediction_dl_percent":5.76,"std":0.52},{"year":2026,"prediction_dl_percent":5.29,"std":0.52,"prediction_type":"linear_projection_from_2024_2025"}]},"Surabaya|Wiyung":{"gid_3":"IDN.11.35.29_1","name_2":"Surabaya","name_3":"Wiyung","series":[{"year":2018,"prediction_dl_percent":3.785,"std":0.133},{"year":2019,"prediction_dl_percent":3.324,"std":0.065},{"year":2020,"prediction_dl_percent":3.35,"std":0.079},{"year":2021,"prediction_dl_percent":3.43,"std":0.051},{"year":2022,"prediction_dl_percent":3.547,"std":0.116},{"year":2023,"prediction_dl_percent":4.02,"std":0.31},{"year":2024,"prediction_dl_percent":4.157,"std":0.316},{"year":2025,"prediction_dl_percent":4.12,"std":0.252},{"year":2026,"prediction_dl_percent":4.083,"std":0.252,"prediction_type":"linear_projection_from_2024_2025"}]},"Surabaya|Benowo":{"gid_3":"IDN.11.35.2_1","name_2":"Surabaya","name_3":"Benowo","series":[{"year":2018,"prediction_dl_percent":4.377,"std":0.021},{"year":2019,"prediction_dl_percent":3.4,"std":0.06},{"year":2020,"prediction_dl_percent":3.491,"std":0.064},{"year":2021,"prediction_dl_percent":3.637,"std":0.03},{"year":2022,"prediction_dl_percent":3.794,"std":0.159},{"year":2023,"prediction_dl_percent":4.354,"std":0.251},{"year":2024,"prediction_dl_percent":4.599,"std":0.243},{"year":2025,"prediction_dl_percent":4.546,"std":0.195},{"year":2026,"prediction_dl_percent":4.493,"std":0.195,"prediction_type":"linear_projection_from_2024_2025"}]},"Surabaya|Wonocolo":{"gid_3":"IDN.11.35.30_1","name_2":"Surabaya","name_3":"Wonocolo","series":[{"year":2018,"prediction_dl_percent":3.663,"std":0.084},{"year":2019,"prediction_dl_percent":3.232,"std":0.025},{"year":2020,"prediction_dl_percent":3.33,"std":0.104},{"year":2021,"prediction_dl_percent":3.389,"std":0.1},{"year":2022,"prediction_dl_percent":3.374,"std":0.185},{"year":2023,"prediction_dl_percent":3.785,"std":0.426},{"year":2024,"prediction_dl_percent":3.835,"std":0.412},{"year":2025,"prediction_dl_percent":3.785,"std":0.34},{"year":2026,"prediction_dl_percent":3.735,"std":0.34,"prediction_type":"linear_projection_from_2024_2025"}]},"Surabaya|Wonokromo":{"gid_3":"IDN.11.35.31_1","name_2":"Surabaya","name_3":"Wonokromo","series":[{"year":2018,"prediction_dl_percent":8.647,"std":0.466},{"year":2019,"prediction_dl_percent":4.839,"std":0.157},{"year":2020,"prediction_dl_percent":4.339,"std":0.111},{"year":2021,"prediction_dl_percent":4.474,"std":0.135},{"year":2022,"prediction_dl_percent":4.396,"std":0.149},{"year":2023,"prediction_dl_percent":6.201,"std":0.68},{"year":2024,"prediction_dl_percent":6.23,"std":0.586},{"year":2025,"prediction_dl_percent":5.76,"std":0.52},{"year":2026,"prediction_dl_percent":5.29,"std":0.52,"prediction_type":"linear_projection_from_2024_2025"}]},"Surabaya|Bubutan":{"gid_3":"IDN.11.35.3_1","name_2":"Surabaya","name_3":"Bubutan","series":[{"year":2018,"prediction_dl_percent":8.647,"std":0.466},{"year":2019,"prediction_dl_percent":4.839,"std":0.157},{"year":2020,"prediction_dl_percent":4.339,"std":0.111},{"year":2021,"prediction_dl_percent":4.474,"std":0.135},{"year":2022,"prediction_dl_percent":4.396,"std":0.149},{"year":2023,"prediction_dl_percent":6.201,"std":0.68},{"year":2024,"prediction_dl_percent":6.23,"std":0.586},{"year":2025,"prediction_dl_percent":5.76,"std":0.52},{"year":2026,"prediction_dl_percent":5.29,"std":0.52,"prediction_type":"linear_projection_from_2024_2025"}]},"Surabaya|Bulak":{"gid_3":"IDN.11.35.4_1","name_2":"Surabaya","name_3":"Bulak","series":[{"year":2018,"prediction_dl_percent":5.306,"std":0.244},{"year":2019,"prediction_dl_percent":3.689,"std":0.091},{"year":2020,"prediction_dl_percent":3.804,"std":0.17},{"year":2021,"prediction_dl_percent":3.915,"std":0.108},{"year":2022,"prediction_dl_percent":4.207,"std":0.169},{"year":2023,"prediction_dl_percent":5.03,"std":0.465},{"year":2024,"prediction_dl_percent":5.181,"std":0.406},{"year":2025,"prediction_dl_percent":5.01,"std":0.314},{"year":2026,"prediction_dl_percent":4.839,"std":0.314,"prediction_type":"linear_projection_from_2024_2025"}]},"Surabaya|DukuhPakis":{"gid_3":"IDN.11.35.5_1","name_2":"Surabaya","name_3":"DukuhPakis","series":[{"year":2018,"prediction_dl_percent":3.639,"std":0.111},{"year":2019,"prediction_dl_percent":3.261,"std":0.028},{"year":2020,"prediction_dl_percent":3.302,"std":0.096},{"year":2021,"prediction_dl_percent":3.401,"std":0.063},{"year":2022,"prediction_dl_percent":3.56,"std":0.151},{"year":2023,"prediction_dl_percent":4.024,"std":0.333},{"year":2024,"prediction_dl_percent":4.088,"std":0.367},{"year":2025,"prediction_dl_percent":4.062,"std":0.318},{"year":2026,"prediction_dl_percent":4.036,"std":0.318,"prediction_type":"linear_projection_from_2024_2025"}]},"Surabaya|Gayungan":{"gid_3":"IDN.11.35.6_1","name_2":"Surabaya","name_3":"Gayungan","series":[{"year":2018,"prediction_dl_percent":8.647,"std":0.466},{"year":2019,"prediction_dl_percent":4.839,"std":0.157},{"year":2020,"prediction_dl_percent":4.339,"std":0.111},{"year":2021,"prediction_dl_percent":4.474,"std":0.135},{"year":2022,"prediction_dl_percent":4.396,"std":0.149},{"year":2023,"prediction_dl_percent":6.201,"std":0.68},{"year":2024,"prediction_dl_percent":6.23,"std":0.586},{"year":2025,"prediction_dl_percent":5.76,"std":0.52},{"year":2026,"prediction_dl_percent":5.29,"std":0.52,"prediction_type":"linear_projection_from_2024_2025"}]},"Surabaya|Genteng":{"gid_3":"IDN.11.35.7_1","name_2":"Surabaya","name_3":"Genteng","series":[{"year":2018,"prediction_dl_percent":3.587,"std":0.116},{"year":2019,"prediction_dl_percent":3.233,"std":0.043},{"year":2020,"prediction_dl_percent":3.321,"std":0.128},{"year":2021,"prediction_dl_percent":3.326,"std":0.046},{"year":2022,"prediction_dl_percent":3.358,"std":0.14},{"year":2023,"prediction_dl_percent":3.705,"std":0.318},{"year":2024,"prediction_dl_percent":3.829,"std":0.303},{"year":2025,"prediction_dl_percent":3.8,"std":0.207},{"year":2026,"prediction_dl_percent":3.771,"std":0.207,"prediction_type":"linear_projection_from_2024_2025"}]},"Surabaya|Gubeng":{"gid_3":"IDN.11.35.8_1","name_2":"Surabaya","name_3":"Gubeng","series":[{"year":2018,"prediction_dl_percent":8.647,"std":0.466},{"year":2019,"prediction_dl_percent":4.839,"std":0.157},{"year":2020,"prediction_dl_percent":4.339,"std":0.111},{"year":2021,"prediction_dl_percent":4.474,"std":0.135},{"year":2022,"prediction_dl_percent":4.396,"std":0.149},{"year":2023,"prediction_dl_percent":6.201,"std":0.68},{"year":2024,"prediction_dl_percent":6.23,"std":0.586},{"year":2025,"prediction_dl_percent":5.76,"std":0.52},{"year":2026,"prediction_dl_percent":5.29,"std":0.52,"prediction_type":"linear_projection_from_2024_2025"}]},"Surabaya|GunungAnyar":{"gid_3":"IDN.11.35.9_1","name_2":"Surabaya","name_3":"GunungAnyar","series":[{"year":2018,"prediction_dl_percent":8.647,"std":0.466},{"year":2019,"prediction_dl_percent":4.839,"std":0.157},{"year":2020,"prediction_dl_percent":4.339,"std":0.111},{"year":2021,"prediction_dl_percent":4.474,"std":0.135},{"year":2022,"prediction_dl_percent":4.396,"std":0.149},{"year":2023,"prediction_dl_percent":6.201,"std":0.68},{"year":2024,"prediction_dl_percent":6.23,"std":0.586},{"year":2025,"prediction_dl_percent":5.76,"std":0.52},{"year":2026,"prediction_dl_percent":5.29,"std":0.52,"prediction_type":"linear_projection_from_2024_2025"}]},"Gresik|Kedamean":{"gid_3":"IDN.11.7.10_1","name_2":"Gresik","name_3":"Kedamean","series":[{"year":2018,"prediction_dl_percent":18.566,"std":0.124},{"year":2019,"prediction_dl_percent":15.609,"std":0.299},{"year":2020,"prediction_dl_percent":15.972,"std":0.537},{"year":2021,"prediction_dl_percent":14.933,"std":0.736},{"year":2022,"prediction_dl_percent":14.296,"std":0.599},{"year":2023,"prediction_dl_percent":13.162,"std":0.661},{"year":2024,"prediction_dl_percent":12.371,"std":1.246},{"year":2025,"prediction_dl_percent":12.254,"std":0.447},{"year":2026,"prediction_dl_percent":12.137,"std":0.447,"prediction_type":"linear_projection_from_2024_2025"}]},"Gresik|Manyar":{"gid_3":"IDN.11.7.11_1","name_2":"Gresik","name_3":"Manyar","series":[{"year":2018,"prediction_dl_percent":16.286,"std":0.292},{"year":2019,"prediction_dl_percent":10.464,"std":0.275},{"year":2020,"prediction_dl_percent":11.992,"std":0.588},{"year":2021,"prediction_dl_percent":11.086,"std":0.213},{"year":2022,"prediction_dl_percent":11.958,"std":0.249},{"year":2023,"prediction_dl_percent":9.579,"std":0.603},{"year":2024,"prediction_dl_percent":8.733,"std":0.628},{"year":2025,"prediction_dl_percent":9.886,"std":0.445},{"year":2026,"prediction_dl_percent":11.039,"std":0.445,"prediction_type":"linear_projection_from_2024_2025"}]},"Gresik|Menganti":{"gid_3":"IDN.11.7.12_1","name_2":"Gresik","name_3":"Menganti","series":[{"year":2018,"prediction_dl_percent":16.245,"std":0.604},{"year":2019,"prediction_dl_percent":8.002,"std":0.578},{"year":2020,"prediction_dl_percent":10.118,"std":0.42},{"year":2021,"prediction_dl_percent":9.114,"std":0.25},{"year":2022,"prediction_dl_percent":10.47,"std":0.215},{"year":2023,"prediction_dl_percent":6.655,"std":0.504},{"year":2024,"prediction_dl_percent":6.529,"std":0.405},{"year":2025,"prediction_dl_percent":7.785,"std":0.234},{"year":2026,"prediction_dl_percent":9.041,"std":0.234,"prediction_type":"linear_projection_from_2024_2025"}]},"Gresik|Panceng":{"gid_3":"IDN.11.7.13_1","name_2":"Gresik","name_3":"Panceng","series":[{"year":2018,"prediction_dl_percent":18.985,"std":0.124},{"year":2019,"prediction_dl_percent":16.726,"std":0.43},{"year":2020,"prediction_dl_percent":16.899,"std":0.389},{"year":2021,"prediction_dl_percent":16.345,"std":0.441},{"year":2022,"prediction_dl_percent":15.869,"std":0.163},{"year":2023,"prediction_dl_percent":15.708,"std":0.184},{"year":2024,"prediction_dl_percent":15.289,"std":0.411},{"year":2025,"prediction_dl_percent":15.305,"std":0.115},{"year":2026,"prediction_dl_percent":15.321,"std":0.115,"prediction_type":"linear_projection_from_2024_2025"}]},"Gresik|Sangkapura":{"gid_3":"IDN.11.7.14_1","name_2":"Gresik","name_3":"Sangkapura","series":[{"year":2018,"prediction_dl_percent":8.92,"std":0.55},{"year":2019,"prediction_dl_percent":5.181,"std":0.437},{"year":2020,"prediction_dl_percent":5.876,"std":0.293},{"year":2021,"prediction_dl_percent":5.598,"std":0.499},{"year":2022,"prediction_dl_percent":5.712,"std":0.497},{"year":2023,"prediction_dl_percent":5.731,"std":0.563},{"year":2024,"prediction_dl_percent":5.543,"std":0.498},{"year":2025,"prediction_dl_percent":5.65,"std":0.541},{"year":2026,"prediction_dl_percent":5.757,"std":0.541,"prediction_type":"linear_projection_from_2024_2025"}]},"Gresik|Sidayu":{"gid_3":"IDN.11.7.15_1","name_2":"Gresik","name_3":"Sidayu","series":[{"year":2018,"prediction_dl_percent":18.673,"std":0.022},{"year":2019,"prediction_dl_percent":15.595,"std":0.302},{"year":2020,"prediction_dl_percent":15.984,"std":0.26},{"year":2021,"prediction_dl_percent":15.097,"std":0.36},{"year":2022,"prediction_dl_percent":15.064,"std":0.159},{"year":2023,"prediction_dl_percent":13.981,"std":0.137},{"year":2024,"prediction_dl_percent":13.114,"std":0.067},{"year":2025,"prediction_dl_percent":13.498,"std":0.239},{"year":2026,"prediction_dl_percent":13.882,"std":0.239,"prediction_type":"linear_projection_from_2024_2025"}]},"Gresik|Tambak":{"gid_3":"IDN.11.7.16_1","name_2":"Gresik","name_3":"Tambak","series":[{"year":2018,"prediction_dl_percent":8.92,"std":0.55},{"year":2019,"prediction_dl_percent":5.181,"std":0.437},{"year":2020,"prediction_dl_percent":5.876,"std":0.293},{"year":2021,"prediction_dl_percent":5.598,"std":0.499},{"year":2022,"prediction_dl_percent":5.712,"std":0.497},{"year":2023,"prediction_dl_percent":5.731,"std":0.563},{"year":2024,"prediction_dl_percent":5.543,"std":0.498},{"year":2025,"prediction_dl_percent":5.65,"std":0.541},{"year":2026,"prediction_dl_percent":5.757,"std":0.541,"prediction_type":"linear_projection_from_2024_2025"}]},"Gresik|Ujungpangkah":{"gid_3":"IDN.11.7.17_1","name_2":"Gresik","name_3":"Ujungpangkah","series":[{"year":2018,"prediction_dl_percent":18.76,"std":0.022},{"year":2019,"prediction_dl_percent":15.944,"std":0.365},{"year":2020,"prediction_dl_percent":16.151,"std":0.193},{"year":2021,"prediction_dl_percent":15.493,"std":0.281},{"year":2022,"prediction_dl_percent":14.772,"std":0.307},{"year":2023,"prediction_dl_percent":14.651,"std":0.49},{"year":2024,"prediction_dl_percent":14.452,"std":0.299},{"year":2025,"prediction_dl_percent":14.189,"std":0.435},{"year":2026,"prediction_dl_percent":13.926,"std":0.435,"prediction_type":"linear_projection_from_2024_2025"}]},"Gresik|Wringinanom":{"gid_3":"IDN.11.7.18_1","name_2":"Gresik","name_3":"Wringinanom","series":[{"year":2018,"prediction_dl_percent":17.699,"std":0.11},{"year":2019,"prediction_dl_percent":9.643,"std":1.026},{"year":2020,"prediction_dl_percent":13.346,"std":0.441},{"year":2021,"prediction_dl_percent":12.538,"std":0.472},{"year":2022,"prediction_dl_percent":11.783,"std":0.523},{"year":2023,"prediction_dl_percent":10.363,"std":0.571},{"year":2024,"prediction_dl_percent":9.721,"std":0.597},{"year":2025,"prediction_dl_percent":11.144,"std":0.233},{"year":2026,"prediction_dl_percent":12.567,"std":0.233,"prediction_type":"linear_projection_from_2024_2025"}]},"Gresik|Balongpanggang":{"gid_3":"IDN.11.7.1_1","name_2":"Gresik","name_3":"Balongpanggang","series":[{"year":2018,"prediction_dl_percent":18.893,"std":0.095},{"year":2019,"prediction_dl_percent":16.108,"std":0.364},{"year":2020,"prediction_dl_percent":16.543,"std":0.377},{"year":2021,"prediction_dl_percent":15.895,"std":0.475},{"year":2022,"prediction_dl_percent":15.683,"std":0.265},{"year":2023,"prediction_dl_percent":14.84,"std":0.541},{"year":2024,"prediction_dl_percent":14.507,"std":0.812},{"year":2025,"prediction_dl_percent":14.232,"std":0.318},{"year":2026,"prediction_dl_percent":13.957,"std":0.318,"prediction_type":"linear_projection_from_2024_2025"}]},"Gresik|Benjeng":{"gid_3":"IDN.11.7.2_1","name_2":"Gresik","name_3":"Benjeng","series":[{"year":2018,"prediction_dl_percent":18.822,"std":0.079},{"year":2019,"prediction_dl_percent":15.313,"std":0.056},{"year":2020,"prediction_dl_percent":16.063,"std":0.319},{"year":2021,"prediction_dl_percent":15.204,"std":0.44},{"year":2022,"prediction_dl_percent":15.432,"std":0.332},{"year":2023,"prediction_dl_percent":14.059,"std":0.757},{"year":2024,"prediction_dl_percent":13.214,"std":0.932},{"year":2025,"prediction_dl_percent":13.778,"std":0.349},{"year":2026,"prediction_dl_percent":14.342,"std":0.349,"prediction_type":"linear_projection_from_2024_2025"}]},"Gresik|Bungah":{"gid_3":"IDN.11.7.3_1","name_2":"Gresik","name_3":"Bungah","series":[{"year":2018,"prediction_dl_percent":18.642,"std":0.103},{"year":2019,"prediction_dl_percent":15.905,"std":0.504},{"year":2020,"prediction_dl_percent":16.113,"std":0.351},{"year":2021,"prediction_dl_percent":15.639,"std":0.388},{"year":2022,"prediction_dl_percent":14.88,"std":0.502},{"year":2023,"prediction_dl_percent":14.983,"std":0.491},{"year":2024,"prediction_dl_percent":14.833,"std":0.274},{"year":2025,"prediction_dl_percent":14.312,"std":0.632},{"year":2026,"prediction_dl_percent":13.791,"std":0.632,"prediction_type":"linear_projection_from_2024_2025"}]},"Gresik|Cerme":{"gid_3":"IDN.11.7.4_1","name_2":"Gresik","name_3":"Cerme","series":[{"year":2018,"prediction_dl_percent":18.512,"std":0.135},{"year":2019,"prediction_dl_percent":14.81,"std":0.062},{"year":2020,"prediction_dl_percent":15.63,"std":0.25},{"year":2021,"prediction_dl_percent":13.878,"std":0.116},{"year":2022,"prediction_dl_percent":14.539,"std":0.059},{"year":2023,"prediction_dl_percent":12.499,"std":0.725},{"year":2024,"prediction_dl_percent":12.109,"std":0.397},{"year":2025,"prediction_dl_percent":12.115,"std":1.149},{"year":2026,"prediction_dl_percent":12.121,"std":1.149,"prediction_type":"linear_projection_from_2024_2025"}]},"Gresik|Driyorejo":{"gid_3":"IDN.11.7.5_1","name_2":"Gresik","name_3":"Driyorejo","series":[{"year":2018,"prediction_dl_percent":7.911,"std":0.897},{"year":2019,"prediction_dl_percent":4.521,"std":0.189},{"year":2020,"prediction_dl_percent":5.518,"std":0.794},{"year":2021,"prediction_dl_percent":5.878,"std":0.47},{"year":2022,"prediction_dl_percent":6.855,"std":0.522},{"year":2023,"prediction_dl_percent":5.153,"std":0.291},{"year":2024,"prediction_dl_percent":5.017,"std":0.283},{"year":2025,"prediction_dl_percent":5.592,"std":0.365},{"year":2026,"prediction_dl_percent":6.167,"std":0.365,"prediction_type":"linear_projection_from_2024_2025"}]},"Gresik|Duduksampeyan":{"gid_3":"IDN.11.7.6_1","name_2":"Gresik","name_3":"Duduksampeyan","series":[{"year":2018,"prediction_dl_percent":18.724,"std":0.037},{"year":2019,"prediction_dl_percent":15.688,"std":0.612},{"year":2020,"prediction_dl_percent":15.905,"std":0.424},{"year":2021,"prediction_dl_percent":15.519,"std":0.31},{"year":2022,"prediction_dl_percent":15.087,"std":0.262},{"year":2023,"prediction_dl_percent":14.898,"std":0.356},{"year":2024,"prediction_dl_percent":14.538,"std":0.298},{"year":2025,"prediction_dl_percent":14.231,"std":0.5},{"year":2026,"prediction_dl_percent":13.924,"std":0.5,"prediction_type":"linear_projection_from_2024_2025"}]},"Gresik|Dukun":{"gid_3":"IDN.11.7.7_1","name_2":"Gresik","name_3":"Dukun","series":[{"year":2018,"prediction_dl_percent":18.841,"std":0.085},{"year":2019,"prediction_dl_percent":16.316,"std":0.475},{"year":2020,"prediction_dl_percent":16.382,"std":0.369},{"year":2021,"prediction_dl_percent":15.92,"std":0.389},{"year":2022,"prediction_dl_percent":15.501,"std":0.06},{"year":2023,"prediction_dl_percent":15.306,"std":0.113},{"year":2024,"prediction_dl_percent":15.042,"std":0.142},{"year":2025,"prediction_dl_percent":14.455,"std":0.373},{"year":2026,"prediction_dl_percent":13.868,"std":0.373,"prediction_type":"linear_projection_from_2024_2025"}]},"Gresik|Gresik":{"gid_3":"IDN.11.7.8_1","name_2":"Gresik","name_3":"Gresik","series":[{"year":2018,"prediction_dl_percent":6.096,"std":0.375},{"year":2019,"prediction_dl_percent":4.221,"std":0.152},{"year":2020,"prediction_dl_percent":4.911,"std":0.16},{"year":2021,"prediction_dl_percent":4.992,"std":0.291},{"year":2022,"prediction_dl_percent":5.453,"std":0.428},{"year":2023,"prediction_dl_percent":5.246,"std":0.308},{"year":2024,"prediction_dl_percent":5.084,"std":0.279},{"year":2025,"prediction_dl_percent":5.236,"std":0.274},{"year":2026,"prediction_dl_percent":5.388,"std":0.274,"prediction_type":"linear_projection_from_2024_2025"}]},"Gresik|Kebomas":{"gid_3":"IDN.11.7.9_1","name_2":"Gresik","name_3":"Kebomas","series":[{"year":2018,"prediction_dl_percent":6.951,"std":0.583},{"year":2019,"prediction_dl_percent":4.48,"std":0.335},{"year":2020,"prediction_dl_percent":5.417,"std":0.501},{"year":2021,"prediction_dl_percent":5.328,"std":0.321},{"year":2022,"prediction_dl_percent":6.711,"std":0.352},{"year":2023,"prediction_dl_percent":5.279,"std":0.461},{"year":2024,"prediction_dl_percent":5.254,"std":0.374},{"year":2025,"prediction_dl_percent":5.481,"std":0.446},{"year":2026,"prediction_dl_percent":5.708,"std":0.446,"prediction_type":"linear_projection_from_2024_2025"}]}},"kabupaten":{"Bangkalan":{"series":[{"year":2018,"prediction":15.02,"error":0.137,"bps":19.59},{"year":2019,"prediction":19.039,"error":0.141,"bps":18.9},{"year":2020,"prediction":19.099,"error":0.14,"bps":20.56},{"year":2021,"prediction":19.113,"error":0.13,"bps":21.57},{"year":2022,"prediction":19.078,"error":0.133,"bps":19.44},{"year":2023,"prediction":18.96,"error":0.161,"bps":19.35},{"year":2024,"prediction":18.967,"error":0.135,"bps":18.66},{"year":2025,"prediction":17.892,"error":0.469,"bps":18.25},{"year":2026,"prediction":16.817,"error":0.469,"bps":null,"prediction_type":"linear_projection_from_2024_2025"}]},"Gresik":{"series":[{"year":2018,"prediction":15.358,"error":0.075,"bps":11.89},{"year":2019,"prediction":11.65,"error":0.115,"bps":11.35},{"year":2020,"prediction":12.483,"error":0.157,"bps":12.4},{"year":2021,"prediction":11.892,"error":0.087,"bps":12.42},{"year":2022,"prediction":11.988,"error":0.061,"bps":11.06},{"year":2023,"prediction":10.99,"error":0.322,"bps":10.96},{"year":2024,"prediction":10.605,"error":0.313,"bps":10.32},{"year":2025,"prediction":10.822,"error":0.228,"bps":9.95},{"year":2026,"prediction":11.039,"error":0.228,"bps":null,"prediction_type":"linear_projection_from_2024_2025"}]},"Surabaya":{"series":[{"year":2018,"prediction":6.496,"error":0.146,"bps":4.88},{"year":2019,"prediction":4.188,"error":0.141,"bps":4.51},{"year":2020,"prediction":3.997,"error":0.079,"bps":5.02},{"year":2021,"prediction":4.064,"error":0.059,"bps":5.23},{"year":2022,"prediction":4.192,"error":0.048,"bps":4.72},{"year":2023,"prediction":5.191,"error":0.432,"bps":4.65},{"year":2024,"prediction":5.326,"error":0.363,"bps":3.96},{"year":2025,"prediction":5.074,"error":0.311,"bps":3.56},{"year":2026,"prediction":4.822,"error":0.311,"bps":null,"prediction_type":"linear_projection_from_2024_2025"}]}},"shap_kecamatan":{},"shap_kabupaten":{},"shap_global":[{"feature":"nlp_freq_Bencana_Kerentanan","modality":"NLP","label":"NLP: Bencana Kerentanan","mean_abs_shap":0.507886,"mean_signed_shap":-0.003815},{"feature":"img_emb_030","modality":"IMAGE","label":"Image embedding 030","mean_abs_shap":0.502653,"mean_signed_shap":0.010138},{"feature":"img_emb_019","modality":"IMAGE","label":"Image embedding 019","mean_abs_shap":0.495827,"mean_signed_shap":0.004721},{"feature":"img_emb_010","modality":"IMAGE","label":"Image embedding 010","mean_abs_shap":0.446861,"mean_signed_shap":0.01888},{"feature":"img_emb_017","modality":"IMAGE","label":"Image embedding 017","mean_abs_shap":0.445442,"mean_signed_shap":-0.009009},{"feature":"img_emb_021","modality":"IMAGE","label":"Image embedding 021","mean_abs_shap":0.444532,"mean_signed_shap":0.007175},{"feature":"img_emb_008","modality":"IMAGE","label":"Image embedding 008","mean_abs_shap":0.41625,"mean_signed_shap":0.01767},{"feature":"img_emb_000","modality":"IMAGE","label":"Image embedding 000","mean_abs_shap":0.409512,"mean_signed_shap":-0.024434},{"feature":"nlp_freq_Perumahan_Sanitasi","modality":"NLP","label":"NLP: Perumahan Sanitasi","mean_abs_shap":0.399946,"mean_signed_shap":-0.00652},{"feature":"img_emb_009","modality":"IMAGE","label":"Image embedding 009","mean_abs_shap":0.376404,"mean_signed_shap":0.00613},{"feature":"img_emb_024","modality":"IMAGE","label":"Image embedding 024","mean_abs_shap":0.375174,"mean_signed_shap":0.004995},{"feature":"img_emb_004","modality":"IMAGE","label":"Image embedding 004","mean_abs_shap":0.33463,"mean_signed_shap":-0.023401},{"feature":"img_emb_020","modality":"IMAGE","label":"Image embedding 020","mean_abs_shap":0.313938,"mean_signed_shap":0.011491},{"feature":"nlp_freq_Pendidikan","modality":"NLP","label":"NLP: Pendidikan","mean_abs_shap":0.286245,"mean_signed_shap":0.002108},{"feature":"img_emb_006","modality":"IMAGE","label":"Image embedding 006","mean_abs_shap":0.278407,"mean_signed_shap":0.006607},{"feature":"img_emb_016","modality":"IMAGE","label":"Image embedding 016","mean_abs_shap":0.271671,"mean_signed_shap":0.005382},{"feature":"nlp_freq_Konflik_Kriminalitas_Sosial","modality":"NLP","label":"NLP: Konflik Kriminalitas Sosial","mean_abs_shap":0.26491,"mean_signed_shap":0.012997},{"feature":"img_emb_029","modality":"IMAGE","label":"Image embedding 029","mean_abs_shap":0.25988,"mean_signed_shap":0.005718},{"feature":"img_emb_014","modality":"IMAGE","label":"Image embedding 014","mean_abs_shap":0.23534,"mean_signed_shap":-0.036685},{"feature":"img_emb_013","modality":"IMAGE","label":"Image embedding 013","mean_abs_shap":0.227686,"mean_signed_shap":0.006328},{"feature":"img_emb_025","modality":"IMAGE","label":"Image embedding 025","mean_abs_shap":0.223953,"mean_signed_shap":-0.01049},{"feature":"mask_image","modality":"IMAGE","label":"Image Availability","mean_abs_shap":0.22123,"mean_signed_shap":-0.014677},{"feature":"img_emb_022","modality":"IMAGE","label":"Image embedding 022","mean_abs_shap":0.217343,"mean_signed_shap":-0.008966},{"feature":"nlp_freq_Infrastruktur_Akses","modality":"NLP","label":"NLP: Infrastruktur Akses","mean_abs_shap":0.20535,"mean_signed_shap":-0.002692},{"feature":"nlp_freq_Kebijakan_Anggaran","modality":"NLP","label":"NLP: Kebijakan Anggaran","mean_abs_shap":0.19811,"mean_signed_shap":-0.005096},{"feature":"img_emb_015","modality":"IMAGE","label":"Image embedding 015","mean_abs_shap":0.194176,"mean_signed_shap":-0.010887},{"feature":"img_emb_011","modality":"IMAGE","label":"Image embedding 011","mean_abs_shap":0.187522,"mean_signed_shap":0.003546},{"feature":"img_emb_031","modality":"IMAGE","label":"Image embedding 031","mean_abs_shap":0.183188,"mean_signed_shap":0.002328},{"feature":"img_emb_003","modality":"IMAGE","label":"Image embedding 003","mean_abs_shap":0.174519,"mean_signed_shap":-0.012451},{"feature":"img_emb_007","modality":"IMAGE","label":"Image embedding 007","mean_abs_shap":0.167656,"mean_signed_shap":0.009671},{"feature":"img_emb_028","modality":"IMAGE","label":"Image embedding 028","mean_abs_shap":0.155572,"mean_signed_shap":0.003019},{"feature":"img_emb_018","modality":"IMAGE","label":"Image embedding 018","mean_abs_shap":0.151776,"mean_signed_shap":0.011231},{"feature":"img_emb_026","modality":"IMAGE","label":"Image embedding 026","mean_abs_shap":0.143387,"mean_signed_shap":-0.003928},{"feature":"img_emb_002","modality":"IMAGE","label":"Image embedding 002","mean_abs_shap":0.141826,"mean_signed_shap":-0.007164},{"feature":"img_emb_012","modality":"IMAGE","label":"Image embedding 012","mean_abs_shap":0.141512,"mean_signed_shap":0.008578},{"feature":"nlp_freq_Kesehatan","modality":"NLP","label":"NLP: Kesehatan","mean_abs_shap":0.13985,"mean_signed_shap":0.007005},{"feature":"nlp_freq_Investasi_Industri","modality":"NLP","label":"NLP: Investasi Industri","mean_abs_shap":0.131303,"mean_signed_shap":-0.002735},{"feature":"nlp_freq_Ketenagakerjaan","modality":"NLP","label":"NLP: Ketenagakerjaan","mean_abs_shap":0.131244,"mean_signed_shap":0.000868},{"feature":"img_emb_023","modality":"IMAGE","label":"Image embedding 023","mean_abs_shap":0.129129,"mean_signed_shap":0.006592},{"feature":"img_emb_001","modality":"IMAGE","label":"Image embedding 001","mean_abs_shap":0.126052,"mean_signed_shap":0.001076},{"feature":"img_emb_027","modality":"IMAGE","label":"Image embedding 027","mean_abs_shap":0.112143,"mean_signed_shap":0.003457},{"feature":"img_emb_005","modality":"IMAGE","label":"Image embedding 005","mean_abs_shap":0.108213,"mean_signed_shap":-0.002702},{"feature":"nlp_freq_Perlindungan_Sosial","modality":"NLP","label":"NLP: Perlindungan Sosial","mean_abs_shap":0.098417,"mean_signed_shap":0.001206},{"feature":"nlp_freq_Ekonomi_Lokal_UMKM","modality":"NLP","label":"NLP: Ekonomi Lokal UMKM","mean_abs_shap":0.078574,"mean_signed_shap":0.002334},{"feature":"nlp_freq_Harga_Pangan_Inflasi","modality":"NLP","label":"NLP: Harga Pangan Inflasi","mean_abs_shap":0.075173,"mean_signed_shap":0.002253},{"feature":"mask_nlp","modality":"NLP","label":"NLP Availability","mean_abs_shap":0,"mean_signed_shap":0},{"feature":"year_standardized_train_only","modality":"TIME","label":"year standardized train only","mean_abs_shap":0,"mean_signed_shap":0}]}