{"meta":{"id":"direct_district__MLP__J3_PCD_IMAGE__feature_aggregation","method":"direct_district","model":"MLP","scenario":"J3_PCD_IMAGE","scenario_label":"PCD + Image","scenario_series":"J","aggregation_weight":"feature_aggregation","supported_regions":["Bangkalan","Banyuwangi","Batu","Blitar","Bojonegoro","Bondowoso","Gresik","Jember","Jombang","Kediri","KotaBlitar","KotaKediri","KotaMadiun","KotaMalang","KotaMojokerto","KotaPasuruan","KotaProbolinggo","Lamongan","Lumajang","Madiun","Magetan","Malang","Mojokerto","Nganjuk","Ngawi","Pacitan","Pamekasan","Pasuruan","Ponorogo","Probolinggo","Sampang","Sidoarjo","Situbondo","Sumenep","Surabaya","Trenggalek","Tuban","Tulungagung"],"supports_kecamatan":false,"has_shap_kecamatan":false,"has_shap_kabupaten":false,"has_shap_global":true,"is_default":false,"is_production":false,"metrics":{"mae":0.565,"rmse":0.728,"r2":0.9691,"spearman":0.9803,"mape":6.54},"metric_weight":"feature_aggregation","label":"MLP J3_PCD_IMAGE"},"kecamatan":{},"kabupaten":{"Bangkalan":{"series":[{"year":2018,"prediction":20.438,"error":0.341,"bps":19.59},{"year":2019,"prediction":19.757,"error":0.12,"bps":18.9},{"year":2020,"prediction":21.355,"error":0.172,"bps":20.56},{"year":2021,"prediction":21.941,"error":0.061,"bps":21.57},{"year":2022,"prediction":19.987,"error":0.346,"bps":19.44},{"year":2023,"prediction":18.514,"error":0.705,"bps":19.35},{"year":2024,"prediction":18.984,"error":0.591,"bps":18.66},{"year":2025,"prediction":18.806,"error":0.826,"bps":18.25},{"year":2026,"prediction":18.628,"error":0.826,"bps":null,"prediction_type":"linear_projection_from_2024_2025"}]},"Banyuwangi":{"series":[{"year":2018,"prediction":8.003,"error":0.084,"bps":7.8},{"year":2019,"prediction":7.493,"error":0.036,"bps":7.52},{"year":2020,"prediction":8.178,"error":0.129,"bps":8.06},{"year":2021,"prediction":8.176,"error":0.192,"bps":8.07},{"year":2022,"prediction":7.506,"error":0.143,"bps":7.51},{"year":2023,"prediction":7.631,"error":0.193,"bps":7.34},{"year":2024,"prediction":7.611,"error":0.266,"bps":6.54},{"year":2025,"prediction":7.243,"error":0.137,"bps":6.13},{"year":2026,"prediction":6.875,"error":0.137,"bps":null,"prediction_type":"linear_projection_from_2024_2025"}]},"Batu":{"series":[{"year":2018,"prediction":3.726,"error":0.149,"bps":3.89},{"year":2019,"prediction":3.675,"error":0.133,"bps":3.81},{"year":2020,"prediction":3.815,"error":0.097,"bps":3.89},{"year":2021,"prediction":3.899,"error":0.04,"bps":4.09},{"year":2022,"prediction":3.696,"error":0.081,"bps":3.79},{"year":2023,"prediction":3.688,"error":0.169,"bps":3.31},{"year":2024,"prediction":3.562,"error":0.16,"bps":3.06},{"year":2025,"prediction":3.457,"error":0.235,"bps":2.86},{"year":2026,"prediction":3.352,"error":0.235,"bps":null,"prediction_type":"linear_projection_from_2024_2025"}]},"Blitar":{"series":[{"year":2018,"prediction":9.672,"error":0.156,"bps":9.72},{"year":2019,"prediction":9.15,"error":0.134,"bps":8.94},{"year":2020,"prediction":9.648,"error":0.165,"bps":9.33},{"year":2021,"prediction":9.737,"error":0.247,"bps":9.65},{"year":2022,"prediction":9.136,"error":0.284,"bps":8.71},{"year":2023,"prediction":8.995,"error":0.015,"bps":8.69},{"year":2024,"prediction":8.913,"error":0.274,"bps":8.16},{"year":2025,"prediction":8.612,"error":0.384,"bps":7.57},{"year":2026,"prediction":8.311,"error":0.384,"bps":null,"prediction_type":"linear_projection_from_2024_2025"}]},"Bojonegoro":{"series":[{"year":2018,"prediction":13.252,"error":0.23,"bps":13.16},{"year":2019,"prediction":12.772,"error":0.398,"bps":12.38},{"year":2020,"prediction":12.837,"error":0.073,"bps":12.87},{"year":2021,"prediction":13.212,"error":0.098,"bps":13.27},{"year":2022,"prediction":12.379,"error":0.015,"bps":12.21},{"year":2023,"prediction":12.591,"error":0.328,"bps":12.18},{"year":2024,"prediction":12.442,"error":0.358,"bps":11.69},{"year":2025,"prediction":13.07,"error":0.185,"bps":11.49},{"year":2026,"prediction":13.698,"error":0.185,"bps":null,"prediction_type":"linear_projection_from_2024_2025"}]},"Bondowoso":{"series":[{"year":2018,"prediction":14.494,"error":0.111,"bps":14.39},{"year":2019,"prediction":13.608,"error":0.15,"bps":13.33},{"year":2020,"prediction":14.353,"error":0.082,"bps":14.17},{"year":2021,"prediction":14.823,"error":0.091,"bps":14.73},{"year":2022,"prediction":13.856,"error":0.108,"bps":13.47},{"year":2023,"prediction":13.485,"error":0.257,"bps":13.34},{"year":2024,"prediction":13.051,"error":0.255,"bps":12.6},{"year":2025,"prediction":12.726,"error":0.079,"bps":12.2},{"year":2026,"prediction":12.401,"error":0.079,"bps":null,"prediction_type":"linear_projection_from_2024_2025"}]},"Gresik":{"series":[{"year":2018,"prediction":11.852,"error":0.148,"bps":11.89},{"year":2019,"prediction":11.553,"error":0.094,"bps":11.35},{"year":2020,"prediction":12.181,"error":0.108,"bps":12.4},{"year":2021,"prediction":12.263,"error":0.08,"bps":12.42},{"year":2022,"prediction":11.203,"error":0.057,"bps":11.06},{"year":2023,"prediction":10.841,"error":0.124,"bps":10.96},{"year":2024,"prediction":10.799,"error":0.277,"bps":10.32},{"year":2025,"prediction":10.358,"error":0.337,"bps":9.95},{"year":2026,"prediction":9.917,"error":0.337,"bps":null,"prediction_type":"linear_projection_from_2024_2025"}]},"Jember":{"series":[{"year":2018,"prediction":10.117,"error":0.183,"bps":9.98},{"year":2019,"prediction":9.545,"error":0.129,"bps":9.25},{"year":2020,"prediction":10.02,"error":0.124,"bps":10.09},{"year":2021,"prediction":10.438,"error":0.259,"bps":10.41},{"year":2022,"prediction":9.705,"error":0.173,"bps":9.39},{"year":2023,"prediction":9.77,"error":0.096,"bps":9.51},{"year":2024,"prediction":9.347,"error":0.249,"bps":9.01},{"year":2025,"prediction":9.185,"error":0.285,"bps":8.67},{"year":2026,"prediction":9.023,"error":0.285,"bps":null,"prediction_type":"linear_projection_from_2024_2025"}]},"Jombang":{"series":[{"year":2018,"prediction":9.544,"error":0.036,"bps":9.56},{"year":2019,"prediction":9.395,"error":0.215,"bps":9.22},{"year":2020,"prediction":9.821,"error":0.118,"bps":9.94},{"year":2021,"prediction":10.054,"error":0.095,"bps":10},{"year":2022,"prediction":9.212,"error":0.09,"bps":9.04},{"year":2023,"prediction":8.849,"error":0.106,"bps":9.15},{"year":2024,"prediction":8.768,"error":0.217,"bps":8.6},{"year":2025,"prediction":8.148,"error":0.206,"bps":8.36},{"year":2026,"prediction":7.528,"error":0.206,"bps":null,"prediction_type":"linear_projection_from_2024_2025"}]},"Kediri":{"series":[{"year":2018,"prediction":11.153,"error":0.141,"bps":11.31},{"year":2019,"prediction":10.591,"error":0.127,"bps":10.42},{"year":2020,"prediction":11.381,"error":0.046,"bps":11.4},{"year":2021,"prediction":11.599,"error":0.088,"bps":11.64},{"year":2022,"prediction":10.57,"error":0.113,"bps":10.65},{"year":2023,"prediction":10.424,"error":0.218,"bps":10.72},{"year":2024,"prediction":10.354,"error":0.197,"bps":9.95},{"year":2025,"prediction":9.933,"error":0.223,"bps":9.81},{"year":2026,"prediction":9.512,"error":0.223,"bps":null,"prediction_type":"linear_projection_from_2024_2025"}]},"KotaBlitar":{"series":[{"year":2018,"prediction":7.568,"error":0.054,"bps":7.44},{"year":2019,"prediction":7.26,"error":0.068,"bps":7.13},{"year":2020,"prediction":7.809,"error":0.027,"bps":7.78},{"year":2021,"prediction":7.807,"error":0.06,"bps":7.89},{"year":2022,"prediction":7.418,"error":0.037,"bps":7.37},{"year":2023,"prediction":6.756,"error":0.282,"bps":7.3},{"year":2024,"prediction":6.564,"error":0.34,"bps":6.75},{"year":2025,"prediction":6.533,"error":0.324,"bps":6.6},{"year":2026,"prediction":6.502,"error":0.324,"bps":null,"prediction_type":"linear_projection_from_2024_2025"}]},"KotaKediri":{"series":[{"year":2018,"prediction":7.691,"error":0.189,"bps":7.68},{"year":2019,"prediction":7.246,"error":0.09,"bps":7.16},{"year":2020,"prediction":7.744,"error":0.088,"bps":7.69},{"year":2021,"prediction":7.666,"error":0.085,"bps":7.75},{"year":2022,"prediction":7.267,"error":0.039,"bps":7.23},{"year":2023,"prediction":6.638,"error":0.127,"bps":7.15},{"year":2024,"prediction":6.481,"error":0.097,"bps":6.51},{"year":2025,"prediction":6.225,"error":0.177,"bps":6.04},{"year":2026,"prediction":5.969,"error":0.177,"bps":null,"prediction_type":"linear_projection_from_2024_2025"}]},"KotaMadiun":{"series":[{"year":2018,"prediction":4.531,"error":0.211,"bps":4.49},{"year":2019,"prediction":4.504,"error":0.16,"bps":4.35},{"year":2020,"prediction":5.059,"error":0.107,"bps":4.98},{"year":2021,"prediction":5.113,"error":0.12,"bps":5.09},{"year":2022,"prediction":4.872,"error":0.115,"bps":4.76},{"year":2023,"prediction":4.378,"error":0.227,"bps":4.74},{"year":2024,"prediction":4.345,"error":0.239,"bps":4.38},{"year":2025,"prediction":4.191,"error":0.239,"bps":3.89},{"year":2026,"prediction":4.037,"error":0.239,"bps":null,"prediction_type":"linear_projection_from_2024_2025"}]},"KotaMalang":{"series":[{"year":2018,"prediction":4.104,"error":0.041,"bps":4.1},{"year":2019,"prediction":4.125,"error":0.032,"bps":4.07},{"year":2020,"prediction":4.601,"error":0.038,"bps":4.44},{"year":2021,"prediction":4.77,"error":0.073,"bps":4.62},{"year":2022,"prediction":4.384,"error":0.031,"bps":4.37},{"year":2023,"prediction":4.16,"error":0.018,"bps":4.26},{"year":2024,"prediction":3.992,"error":0.037,"bps":3.91},{"year":2025,"prediction":3.895,"error":0.042,"bps":3.85},{"year":2026,"prediction":3.798,"error":0.042,"bps":null,"prediction_type":"linear_projection_from_2024_2025"}]},"KotaMojokerto":{"series":[{"year":2018,"prediction":5.376,"error":0.012,"bps":5.5},{"year":2019,"prediction":5.325,"error":0.049,"bps":5.15},{"year":2020,"prediction":6.109,"error":0.05,"bps":6.24},{"year":2021,"prediction":6.363,"error":0.063,"bps":6.39},{"year":2022,"prediction":5.845,"error":0.062,"bps":5.98},{"year":2023,"prediction":5.575,"error":0.089,"bps":5.77},{"year":2024,"prediction":5.418,"error":0.115,"bps":5.57},{"year":2025,"prediction":5.303,"error":0.127,"bps":5.05},{"year":2026,"prediction":5.188,"error":0.127,"bps":null,"prediction_type":"linear_projection_from_2024_2025"}]},"KotaPasuruan":{"series":[{"year":2018,"prediction":6.776,"error":0.036,"bps":6.77},{"year":2019,"prediction":6.671,"error":0.029,"bps":6.46},{"year":2020,"prediction":6.963,"error":0.006,"bps":6.66},{"year":2021,"prediction":6.876,"error":0.138,"bps":6.88},{"year":2022,"prediction":6.495,"error":0.106,"bps":6.37},{"year":2023,"prediction":5.909,"error":0.242,"bps":6.6},{"year":2024,"prediction":5.845,"error":0.117,"bps":6.32},{"year":2025,"prediction":5.639,"error":0.258,"bps":6.18},{"year":2026,"prediction":5.433,"error":0.258,"bps":null,"prediction_type":"linear_projection_from_2024_2025"}]},"KotaProbolinggo":{"series":[{"year":2018,"prediction":7.293,"error":0.085,"bps":7.2},{"year":2019,"prediction":7.058,"error":0.05,"bps":6.91},{"year":2020,"prediction":7.411,"error":0.084,"bps":7.43},{"year":2021,"prediction":7.428,"error":0.056,"bps":7.44},{"year":2022,"prediction":6.913,"error":0.056,"bps":6.65},{"year":2023,"prediction":6.525,"error":0.138,"bps":6.48},{"year":2024,"prediction":6.446,"error":0.149,"bps":6.18},{"year":2025,"prediction":6.22,"error":0.239,"bps":5.69},{"year":2026,"prediction":5.994,"error":0.239,"bps":null,"prediction_type":"linear_projection_from_2024_2025"}]},"Lamongan":{"series":[{"year":2018,"prediction":13.886,"error":0.272,"bps":13.8},{"year":2019,"prediction":13.43,"error":0.133,"bps":13.21},{"year":2020,"prediction":13.783,"error":0.142,"bps":13.85},{"year":2021,"prediction":13.753,"error":0.206,"bps":13.86},{"year":2022,"prediction":12.557,"error":0.123,"bps":12.53},{"year":2023,"prediction":14.248,"error":0.709,"bps":12.42},{"year":2024,"prediction":13.63,"error":0.935,"bps":12.16},{"year":2025,"prediction":12.015,"error":0.421,"bps":12.03},{"year":2026,"prediction":10.4,"error":0.421,"bps":null,"prediction_type":"linear_projection_from_2024_2025"}]},"Lumajang":{"series":[{"year":2018,"prediction":10.021,"error":0.078,"bps":9.98},{"year":2019,"prediction":9.779,"error":0.093,"bps":9.49},{"year":2020,"prediction":10.084,"error":0.121,"bps":9.83},{"year":2021,"prediction":10.388,"error":0.262,"bps":10.05},{"year":2022,"prediction":9.249,"error":0.125,"bps":9.06},{"year":2023,"prediction":9.033,"error":0.091,"bps":8.93},{"year":2024,"prediction":9.006,"error":0.058,"bps":8.65},{"year":2025,"prediction":8.899,"error":0.132,"bps":8.6},{"year":2026,"prediction":8.792,"error":0.132,"bps":null,"prediction_type":"linear_projection_from_2024_2025"}]},"Madiun":{"series":[{"year":2018,"prediction":11.79,"error":0.274,"bps":11.42},{"year":2019,"prediction":10.778,"error":0.045,"bps":10.54},{"year":2020,"prediction":11.474,"error":0.063,"bps":11.46},{"year":2021,"prediction":12.173,"error":0.261,"bps":11.91},{"year":2022,"prediction":11.121,"error":0.11,"bps":10.79},{"year":2023,"prediction":10.058,"error":0.268,"bps":11.04},{"year":2024,"prediction":9.755,"error":0.403,"bps":10.63},{"year":2025,"prediction":9.521,"error":0.799,"bps":10.4},{"year":2026,"prediction":9.287,"error":0.799,"bps":null,"prediction_type":"linear_projection_from_2024_2025"}]},"Magetan":{"series":[{"year":2018,"prediction":10.355,"error":0.143,"bps":10.31},{"year":2019,"prediction":9.864,"error":0.041,"bps":9.61},{"year":2020,"prediction":10.542,"error":0.173,"bps":10.35},{"year":2021,"prediction":10.932,"error":0.067,"bps":10.66},{"year":2022,"prediction":10.034,"error":0.147,"bps":9.84},{"year":2023,"prediction":10.088,"error":0.11,"bps":9.8},{"year":2024,"prediction":10.131,"error":0.216,"bps":9.32},{"year":2025,"prediction":8.97,"error":0.384,"bps":9.14},{"year":2026,"prediction":7.809,"error":0.384,"bps":null,"prediction_type":"linear_projection_from_2024_2025"}]},"Malang":{"series":[{"year":2018,"prediction":10.309,"error":0.057,"bps":10.37},{"year":2019,"prediction":9.778,"error":0.078,"bps":9.47},{"year":2020,"prediction":10.216,"error":0.158,"bps":10.15},{"year":2021,"prediction":10.386,"error":0.105,"bps":10.5},{"year":2022,"prediction":9.713,"error":0.073,"bps":9.55},{"year":2023,"prediction":9.651,"error":0.095,"bps":9.45},{"year":2024,"prediction":9.669,"error":0.062,"bps":8.98},{"year":2025,"prediction":9.173,"error":0.212,"bps":8.78},{"year":2026,"prediction":8.677,"error":0.212,"bps":null,"prediction_type":"linear_projection_from_2024_2025"}]},"Mojokerto":{"series":[{"year":2018,"prediction":10.183,"error":0.094,"bps":10.08},{"year":2019,"prediction":9.975,"error":0.084,"bps":9.75},{"year":2020,"prediction":10.458,"error":0.067,"bps":10.57},{"year":2021,"prediction":10.604,"error":0.091,"bps":10.62},{"year":2022,"prediction":9.768,"error":0.107,"bps":9.71},{"year":2023,"prediction":10.175,"error":0.144,"bps":9.8},{"year":2024,"prediction":9.693,"error":0.115,"bps":9.37},{"year":2025,"prediction":9.06,"error":0.294,"bps":8.79},{"year":2026,"prediction":8.427,"error":0.294,"bps":null,"prediction_type":"linear_projection_from_2024_2025"}]},"Nganjuk":{"series":[{"year":2018,"prediction":12.146,"error":0.158,"bps":12.11},{"year":2019,"prediction":11.528,"error":0.051,"bps":11.24},{"year":2020,"prediction":11.646,"error":0.127,"bps":11.62},{"year":2021,"prediction":11.905,"error":0.119,"bps":11.85},{"year":2022,"prediction":11.044,"error":0.181,"bps":10.7},{"year":2023,"prediction":10.494,"error":0.319,"bps":10.89},{"year":2024,"prediction":10.342,"error":0.294,"bps":10.17},{"year":2025,"prediction":9.122,"error":0.068,"bps":10.06},{"year":2026,"prediction":7.902,"error":0.068,"bps":null,"prediction_type":"linear_projection_from_2024_2025"}]},"Ngawi":{"series":[{"year":2018,"prediction":14.464,"error":0.435,"bps":14.83},{"year":2019,"prediction":14.791,"error":0.177,"bps":14.39},{"year":2020,"prediction":15.294,"error":0.052,"bps":15.44},{"year":2021,"prediction":15.618,"error":0.231,"bps":15.57},{"year":2022,"prediction":14.325,"error":0.073,"bps":14.15},{"year":2023,"prediction":14.375,"error":0.108,"bps":14.4},{"year":2024,"prediction":13.231,"error":0.145,"bps":13.81},{"year":2025,"prediction":14.486,"error":0.21,"bps":13.62},{"year":2026,"prediction":15.741,"error":0.21,"bps":null,"prediction_type":"linear_projection_from_2024_2025"}]},"Pacitan":{"series":[{"year":2018,"prediction":14.489,"error":0.139,"bps":14.19},{"year":2019,"prediction":13.81,"error":0.163,"bps":13.67},{"year":2020,"prediction":14.834,"error":0.191,"bps":14.54},{"year":2021,"prediction":15.105,"error":0.197,"bps":15.11},{"year":2022,"prediction":14.15,"error":0.087,"bps":13.8},{"year":2023,"prediction":14.403,"error":0.188,"bps":13.65},{"year":2024,"prediction":14.2,"error":0.172,"bps":13.08},{"year":2025,"prediction":13.797,"error":0.153,"bps":12.97},{"year":2026,"prediction":13.394,"error":0.153,"bps":null,"prediction_type":"linear_projection_from_2024_2025"}]},"Pamekasan":{"series":[{"year":2018,"prediction":14.22,"error":0.886,"bps":14.47},{"year":2019,"prediction":14.407,"error":0.473,"bps":13.95},{"year":2020,"prediction":15.031,"error":0.307,"bps":14.6},{"year":2021,"prediction":15.231,"error":0.122,"bps":15.3},{"year":2022,"prediction":14.291,"error":0.025,"bps":13.93},{"year":2023,"prediction":12.772,"error":0.459,"bps":13.85},{"year":2024,"prediction":12.627,"error":0.187,"bps":13.41},{"year":2025,"prediction":11.032,"error":0.214,"bps":12.77},{"year":2026,"prediction":9.437,"error":0.214,"bps":null,"prediction_type":"linear_projection_from_2024_2025"}]},"Pasuruan":{"series":[{"year":2018,"prediction":9.499,"error":0.173,"bps":9.45},{"year":2019,"prediction":9.003,"error":0.168,"bps":8.68},{"year":2020,"prediction":9.377,"error":0.16,"bps":9.26},{"year":2021,"prediction":9.628,"error":0.234,"bps":9.7},{"year":2022,"prediction":9.035,"error":0.016,"bps":8.96},{"year":2023,"prediction":8.798,"error":0.128,"bps":9.24},{"year":2024,"prediction":8.42,"error":0.045,"bps":8.63},{"year":2025,"prediction":8.438,"error":0.182,"bps":8.21},{"year":2026,"prediction":8.456,"error":0.182,"bps":null,"prediction_type":"linear_projection_from_2024_2025"}]},"Ponorogo":{"series":[{"year":2018,"prediction":11.233,"error":0.211,"bps":10.36},{"year":2019,"prediction":9.872,"error":0.043,"bps":9.64},{"year":2020,"prediction":10.254,"error":0.077,"bps":9.95},{"year":2021,"prediction":10.223,"error":0.18,"bps":10.26},{"year":2022,"prediction":9.649,"error":0.061,"bps":9.32},{"year":2023,"prediction":8.812,"error":0.111,"bps":9.53},{"year":2024,"prediction":8.583,"error":0.102,"bps":9.11},{"year":2025,"prediction":8.883,"error":0.262,"bps":8.86},{"year":2026,"prediction":9.183,"error":0.262,"bps":null,"prediction_type":"linear_projection_from_2024_2025"}]},"Probolinggo":{"series":[{"year":2018,"prediction":18.814,"error":0.101,"bps":18.71},{"year":2019,"prediction":18.399,"error":0.271,"bps":17.76},{"year":2020,"prediction":18.925,"error":0.208,"bps":18.61},{"year":2021,"prediction":19.19,"error":0.224,"bps":18.91},{"year":2022,"prediction":17.622,"error":0.261,"bps":17.12},{"year":2023,"prediction":17.479,"error":0.179,"bps":17.19},{"year":2024,"prediction":16.772,"error":0.141,"bps":16.45},{"year":2025,"prediction":15.336,"error":0.073,"bps":16.31},{"year":2026,"prediction":13.9,"error":0.073,"bps":null,"prediction_type":"linear_projection_from_2024_2025"}]},"Sampang":{"series":[{"year":2018,"prediction":21.196,"error":0.141,"bps":21.21},{"year":2019,"prediction":21.46,"error":0.085,"bps":20.71},{"year":2020,"prediction":22.555,"error":0.131,"bps":22.78},{"year":2021,"prediction":22.89,"error":0.192,"bps":23.76},{"year":2022,"prediction":22.029,"error":0.14,"bps":21.61},{"year":2023,"prediction":20.411,"error":0.597,"bps":21.76},{"year":2024,"prediction":20.714,"error":0.637,"bps":20.83},{"year":2025,"prediction":20.959,"error":0.638,"bps":20.61},{"year":2026,"prediction":21.204,"error":0.638,"bps":null,"prediction_type":"linear_projection_from_2024_2025"}]},"Sidoarjo":{"series":[{"year":2018,"prediction":5.448,"error":0.072,"bps":5.69},{"year":2019,"prediction":5.315,"error":0.139,"bps":5.32},{"year":2020,"prediction":5.678,"error":0.128,"bps":5.59},{"year":2021,"prediction":5.581,"error":0.089,"bps":5.93},{"year":2022,"prediction":5.251,"error":0.028,"bps":5.36},{"year":2023,"prediction":4.855,"error":0.056,"bps":5},{"year":2024,"prediction":4.795,"error":0.046,"bps":4.53},{"year":2025,"prediction":4.648,"error":0.037,"bps":4.4},{"year":2026,"prediction":4.501,"error":0.037,"bps":null,"prediction_type":"linear_projection_from_2024_2025"}]},"Situbondo":{"series":[{"year":2018,"prediction":11.859,"error":0.143,"bps":11.82},{"year":2019,"prediction":11.504,"error":0.205,"bps":11.2},{"year":2020,"prediction":12.332,"error":0.179,"bps":12.22},{"year":2021,"prediction":12.507,"error":0.193,"bps":12.63},{"year":2022,"prediction":11.84,"error":0.25,"bps":11.78},{"year":2023,"prediction":11.157,"error":0.248,"bps":11.9},{"year":2024,"prediction":10.844,"error":0.332,"bps":11.51},{"year":2025,"prediction":10.698,"error":0.27,"bps":11.17},{"year":2026,"prediction":10.552,"error":0.27,"bps":null,"prediction_type":"linear_projection_from_2024_2025"}]},"Sumenep":{"series":[{"year":2018,"prediction":20.879,"error":0.034,"bps":20.16},{"year":2019,"prediction":19.82,"error":0.195,"bps":19.48},{"year":2020,"prediction":20.681,"error":0.303,"bps":20.18},{"year":2021,"prediction":20.442,"error":0.064,"bps":20.51},{"year":2022,"prediction":19.134,"error":0.231,"bps":18.76},{"year":2023,"prediction":19.398,"error":0.29,"bps":18.7},{"year":2024,"prediction":19.21,"error":0.443,"bps":17.78},{"year":2025,"prediction":18.031,"error":0.948,"bps":17.02},{"year":2026,"prediction":16.852,"error":0.948,"bps":null,"prediction_type":"linear_projection_from_2024_2025"}]},"Surabaya":{"series":[{"year":2018,"prediction":4.768,"error":0.06,"bps":4.88},{"year":2019,"prediction":4.731,"error":0.109,"bps":4.51},{"year":2020,"prediction":5.012,"error":0.049,"bps":5.02},{"year":2021,"prediction":5.149,"error":0.11,"bps":5.23},{"year":2022,"prediction":4.754,"error":0.058,"bps":4.72},{"year":2023,"prediction":4.547,"error":0.038,"bps":4.65},{"year":2024,"prediction":4.451,"error":0.044,"bps":3.96},{"year":2025,"prediction":4.376,"error":0.037,"bps":3.56},{"year":2026,"prediction":4.301,"error":0.037,"bps":null,"prediction_type":"linear_projection_from_2024_2025"}]},"Trenggalek":{"series":[{"year":2018,"prediction":12.501,"error":0.401,"bps":12.02},{"year":2019,"prediction":11.417,"error":0.107,"bps":10.98},{"year":2020,"prediction":11.816,"error":0.113,"bps":11.62},{"year":2021,"prediction":11.991,"error":0.043,"bps":12.14},{"year":2022,"prediction":11.514,"error":0.105,"bps":10.96},{"year":2023,"prediction":11.126,"error":0.237,"bps":10.63},{"year":2024,"prediction":11.101,"error":0.279,"bps":10.5},{"year":2025,"prediction":10.463,"error":0.09,"bps":10.29},{"year":2026,"prediction":9.825,"error":0.09,"bps":null,"prediction_type":"linear_projection_from_2024_2025"}]},"Tuban":{"series":[{"year":2018,"prediction":15.65,"error":0.24,"bps":15.31},{"year":2019,"prediction":15.153,"error":0.27,"bps":14.58},{"year":2020,"prediction":16.066,"error":0.091,"bps":15.91},{"year":2021,"prediction":16.415,"error":0.167,"bps":16.31},{"year":2022,"prediction":15.081,"error":0.081,"bps":15.02},{"year":2023,"prediction":14.698,"error":0.52,"bps":14.91},{"year":2024,"prediction":14.138,"error":0.32,"bps":14.36},{"year":2025,"prediction":14.29,"error":0.168,"bps":14.13},{"year":2026,"prediction":14.442,"error":0.168,"bps":null,"prediction_type":"linear_projection_from_2024_2025"}]},"Tulungagung":{"series":[{"year":2018,"prediction":7.298,"error":0.161,"bps":7.27},{"year":2019,"prediction":7.078,"error":0.243,"bps":6.74},{"year":2020,"prediction":7.519,"error":0.247,"bps":7.33},{"year":2021,"prediction":7.712,"error":0.125,"bps":7.51},{"year":2022,"prediction":6.823,"error":0.324,"bps":6.71},{"year":2023,"prediction":7.173,"error":0.279,"bps":6.53},{"year":2024,"prediction":7.556,"error":0.492,"bps":6.28},{"year":2025,"prediction":6.611,"error":0.186,"bps":5.96},{"year":2026,"prediction":5.666,"error":0.186,"bps":null,"prediction_type":"linear_projection_from_2024_2025"}]}},"shap_kecamatan":{},"shap_kabupaten":{},"shap_global":[{"feature":"pcd_permukiman","modality":"PCD","label":"Settlement","mean_abs_shap":0.869049,"mean_signed_shap":-0.060389},{"feature":"pcd_vegetasi","modality":"PCD","label":"Vegetation","mean_abs_shap":0.842095,"mean_signed_shap":-0.039201},{"feature":"pcd_avg_distance_m","modality":"PCD","label":"Avg Distance","mean_abs_shap":0.790289,"mean_signed_shap":0.002411},{"feature":"img_emb_028","modality":"IMAGE","label":"Image embedding 028","mean_abs_shap":0.672872,"mean_signed_shap":-0.040795},{"feature":"img_emb_014","modality":"IMAGE","label":"Image embedding 014","mean_abs_shap":0.654386,"mean_signed_shap":-0.030263},{"feature":"pcd_NDBI","modality":"PCD","label":"NDBI (Built-up)","mean_abs_shap":0.600319,"mean_signed_shap":0.016938},{"feature":"pcd_air","modality":"PCD","label":"Water","mean_abs_shap":0.594744,"mean_signed_shap":-0.054882},{"feature":"pcd_NTL","modality":"PCD","label":"Night-time Light","mean_abs_shap":0.530208,"mean_signed_shap":0.015813},{"feature":"pcd_jumlah_poi","modality":"PCD","label":"POI Count","mean_abs_shap":0.527076,"mean_signed_shap":-0.00471},{"feature":"pcd_luas_bangunan_km2_opening","modality":"PCD","label":"Built Area Opening","mean_abs_shap":0.516378,"mean_signed_shap":-0.023936},{"feature":"pcd_luas_bangunan_otsu_km2","modality":"PCD","label":"Built Area Otsu","mean_abs_shap":0.500254,"mean_signed_shap":-0.036906},{"feature":"img_emb_002","modality":"IMAGE","label":"Image embedding 002","mean_abs_shap":0.482175,"mean_signed_shap":0.013996},{"feature":"img_emb_006","modality":"IMAGE","label":"Image embedding 006","mean_abs_shap":0.470662,"mean_signed_shap":0.012297},{"feature":"pcd_luas_km2","modality":"PCD","label":"Area","mean_abs_shap":0.459944,"mean_signed_shap":-0.015522},{"feature":"img_emb_023","modality":"IMAGE","label":"Image embedding 023","mean_abs_shap":0.446471,"mean_signed_shap":0.042005},{"feature":"img_emb_005","modality":"IMAGE","label":"Image embedding 005","mean_abs_shap":0.44196,"mean_signed_shap":0.00143},{"feature":"pcd_VANUI","modality":"PCD","label":"VANUI","mean_abs_shap":0.402528,"mean_signed_shap":-0.000921},{"feature":"img_emb_031","modality":"IMAGE","label":"Image embedding 031","mean_abs_shap":0.356361,"mean_signed_shap":0.021025},{"feature":"pcd_density","modality":"PCD","label":"Density","mean_abs_shap":0.349491,"mean_signed_shap":0.032691},{"feature":"img_emb_022","modality":"IMAGE","label":"Image embedding 022","mean_abs_shap":0.335092,"mean_signed_shap":0.014384},{"feature":"img_emb_001","modality":"IMAGE","label":"Image embedding 001","mean_abs_shap":0.330539,"mean_signed_shap":-0.003717},{"feature":"img_emb_017","modality":"IMAGE","label":"Image embedding 017","mean_abs_shap":0.319116,"mean_signed_shap":0.012247},{"feature":"img_emb_007","modality":"IMAGE","label":"Image embedding 007","mean_abs_shap":0.315368,"mean_signed_shap":-0.014065},{"feature":"img_emb_025","modality":"IMAGE","label":"Image embedding 025","mean_abs_shap":0.278191,"mean_signed_shap":0.010849},{"feature":"img_emb_030","modality":"IMAGE","label":"Image embedding 030","mean_abs_shap":0.276946,"mean_signed_shap":0.000814},{"feature":"img_emb_008","modality":"IMAGE","label":"Image embedding 008","mean_abs_shap":0.264266,"mean_signed_shap":-0.014371},{"feature":"pcd_NDVI","modality":"PCD","label":"NDVI (Vegetation)","mean_abs_shap":0.259368,"mean_signed_shap":-0.006231},{"feature":"img_emb_000","modality":"IMAGE","label":"Image embedding 000","mean_abs_shap":0.248433,"mean_signed_shap":-0.003691},{"feature":"img_emb_029","modality":"IMAGE","label":"Image embedding 029","mean_abs_shap":0.246687,"mean_signed_shap":-0.001574},{"feature":"img_emb_013","modality":"IMAGE","label":"Image embedding 013","mean_abs_shap":0.242149,"mean_signed_shap":-0.022195},{"feature":"img_emb_003","modality":"IMAGE","label":"Image embedding 003","mean_abs_shap":0.237389,"mean_signed_shap":-0.010198},{"feature":"img_emb_004","modality":"IMAGE","label":"Image embedding 004","mean_abs_shap":0.222081,"mean_signed_shap":-0.00612},{"feature":"img_emb_018","modality":"IMAGE","label":"Image embedding 018","mean_abs_shap":0.221537,"mean_signed_shap":0.000407},{"feature":"img_emb_027","modality":"IMAGE","label":"Image embedding 027","mean_abs_shap":0.21992,"mean_signed_shap":0.021679},{"feature":"img_emb_016","modality":"IMAGE","label":"Image embedding 016","mean_abs_shap":0.218652,"mean_signed_shap":-0.008774},{"feature":"img_emb_020","modality":"IMAGE","label":"Image embedding 020","mean_abs_shap":0.217875,"mean_signed_shap":-0.002086},{"feature":"img_emb_021","modality":"IMAGE","label":"Image embedding 021","mean_abs_shap":0.215546,"mean_signed_shap":-0.011261},{"feature":"img_emb_015","modality":"IMAGE","label":"Image embedding 015","mean_abs_shap":0.212295,"mean_signed_shap":0.009111},{"feature":"img_emb_009","modality":"IMAGE","label":"Image embedding 009","mean_abs_shap":0.212201,"mean_signed_shap":0.016736},{"feature":"img_emb_026","modality":"IMAGE","label":"Image embedding 026","mean_abs_shap":0.211658,"mean_signed_shap":0.010265},{"feature":"img_emb_024","modality":"IMAGE","label":"Image embedding 024","mean_abs_shap":0.209599,"mean_signed_shap":-0.004378},{"feature":"pcd_NDWI","modality":"PCD","label":"NDWI (Water)","mean_abs_shap":0.205474,"mean_signed_shap":-0.010643},{"feature":"img_emb_012","modality":"IMAGE","label":"Image embedding 012","mean_abs_shap":0.20327,"mean_signed_shap":0.016706},{"feature":"img_emb_011","modality":"IMAGE","label":"Image embedding 011","mean_abs_shap":0.163315,"mean_signed_shap":0.00789},{"feature":"img_emb_010","modality":"IMAGE","label":"Image embedding 010","mean_abs_shap":0.148965,"mean_signed_shap":-0.003902},{"feature":"img_emb_019","modality":"IMAGE","label":"Image embedding 019","mean_abs_shap":0.121976,"mean_signed_shap":-0.004709},{"feature":"mask_image","modality":"IMAGE","label":"Image Availability","mean_abs_shap":0.045442,"mean_signed_shap":0.00052},{"feature":"mask_pcd","modality":"PCD","label":"PCD Availability","mean_abs_shap":0,"mean_signed_shap":0},{"feature":"year_standardized_train_only","modality":"TIME","label":"year standardized train only","mean_abs_shap":0,"mean_signed_shap":0}]}