{"meta":{"id":"mumtaz__GRU__N4_FULL__feature_aggregation","method":"mumtaz","model":"GRU","scenario":"N4_FULL","scenario_label":"Full NLP","scenario_series":"N","aggregation_weight":"feature_aggregation","supported_regions":["Bangkalan","Gresik","Surabaya"],"supports_kecamatan":false,"has_shap_kecamatan":false,"has_shap_kabupaten":false,"has_shap_global":true,"is_default":false,"is_production":false,"metrics":{"mae":1.472,"rmse":1.599,"r2":0.9289,"spearman":0.9429,"mape":23.95},"metric_weight":"feature_aggregation","label":"GRU N4_FULL"},"kecamatan":{},"kabupaten":{"Bangkalan":{"series":[{"year":2018,"prediction":19.394,"error":0.241,"bps":19.59},{"year":2019,"prediction":19.926,"error":0.153,"bps":18.9},{"year":2020,"prediction":19.927,"error":0.154,"bps":20.56},{"year":2021,"prediction":19.914,"error":0.159,"bps":21.57},{"year":2022,"prediction":19.927,"error":0.155,"bps":19.44},{"year":2023,"prediction":19.916,"error":0.161,"bps":19.35},{"year":2024,"prediction":19.917,"error":0.161,"bps":18.66},{"year":2025,"prediction":19.879,"error":0.176,"bps":18.25},{"year":2026,"prediction":19.841,"error":0.176,"bps":null,"prediction_type":"linear_projection_from_2024_2025"}]},"Gresik":{"series":[{"year":2018,"prediction":12.106,"error":0.05,"bps":11.89},{"year":2019,"prediction":11.594,"error":0.117,"bps":11.35},{"year":2020,"prediction":12.149,"error":0.438,"bps":12.4},{"year":2021,"prediction":11.972,"error":0.266,"bps":12.42},{"year":2022,"prediction":11.568,"error":0.066,"bps":11.06},{"year":2023,"prediction":11.312,"error":0.195,"bps":10.96},{"year":2024,"prediction":11.157,"error":0.275,"bps":10.32},{"year":2025,"prediction":11.033,"error":0.332,"bps":9.95},{"year":2026,"prediction":10.909,"error":0.332,"bps":null,"prediction_type":"linear_projection_from_2024_2025"}]},"Surabaya":{"series":[{"year":2018,"prediction":4.848,"error":0.162,"bps":4.88},{"year":2019,"prediction":4.499,"error":0.112,"bps":4.51},{"year":2020,"prediction":4.581,"error":0.083,"bps":5.02},{"year":2021,"prediction":4.672,"error":0.081,"bps":5.23},{"year":2022,"prediction":4.828,"error":0.087,"bps":4.72},{"year":2023,"prediction":4.946,"error":0.118,"bps":4.65},{"year":2024,"prediction":5.361,"error":0.257,"bps":3.96},{"year":2025,"prediction":6.182,"error":0.449,"bps":3.56},{"year":2026,"prediction":7.003,"error":0.449,"bps":null,"prediction_type":"linear_projection_from_2024_2025"}]}},"shap_kecamatan":{},"shap_kabupaten":{},"shap_global":[{"feature":"pcd_avg_distance_m","modality":"PCD","label":"Avg Distance","mean_abs_shap":0.211087,"mean_signed_shap":0.006775},{"feature":"pcd_air","modality":"PCD","label":"Water","mean_abs_shap":0.205839,"mean_signed_shap":0.012033},{"feature":"img_emb_003","modality":"IMAGE","label":"Image embedding 003","mean_abs_shap":0.190946,"mean_signed_shap":0.000911},{"feature":"pcd_luas_bangunan_km2_opening","modality":"PCD","label":"Built Area Opening","mean_abs_shap":0.156489,"mean_signed_shap":0.000042},{"feature":"img_emb_004","modality":"IMAGE","label":"Image embedding 004","mean_abs_shap":0.13234,"mean_signed_shap":-0.000706},{"feature":"img_emb_006","modality":"IMAGE","label":"Image embedding 006","mean_abs_shap":0.128552,"mean_signed_shap":-0.002428},{"feature":"img_emb_016","modality":"IMAGE","label":"Image embedding 016","mean_abs_shap":0.127664,"mean_signed_shap":0.008043},{"feature":"pcd_vegetasi","modality":"PCD","label":"Vegetation","mean_abs_shap":0.109863,"mean_signed_shap":-0.004934},{"feature":"pcd_NDVI","modality":"PCD","label":"NDVI (Vegetation)","mean_abs_shap":0.105532,"mean_signed_shap":0.015751},{"feature":"img_emb_024","modality":"IMAGE","label":"Image embedding 024","mean_abs_shap":0.104497,"mean_signed_shap":-0.002069},{"feature":"img_emb_013","modality":"IMAGE","label":"Image embedding 013","mean_abs_shap":0.10202,"mean_signed_shap":0.002926},{"feature":"pcd_NDWI","modality":"PCD","label":"NDWI (Water)","mean_abs_shap":0.09502,"mean_signed_shap":0.013865},{"feature":"img_emb_010","modality":"IMAGE","label":"Image embedding 010","mean_abs_shap":0.094804,"mean_signed_shap":0.003757},{"feature":"img_emb_029","modality":"IMAGE","label":"Image embedding 029","mean_abs_shap":0.092893,"mean_signed_shap":-0.006964},{"feature":"img_emb_025","modality":"IMAGE","label":"Image embedding 025","mean_abs_shap":0.09149,"mean_signed_shap":-0.003319},{"feature":"img_emb_028","modality":"IMAGE","label":"Image embedding 028","mean_abs_shap":0.089167,"mean_signed_shap":0.002949},{"feature":"img_emb_026","modality":"IMAGE","label":"Image embedding 026","mean_abs_shap":0.086221,"mean_signed_shap":0.00137},{"feature":"nlp_freq_Pendidikan","modality":"NLP","label":"NLP: Pendidikan","mean_abs_shap":0.083939,"mean_signed_shap":0.022192},{"feature":"pcd_luas_km2","modality":"PCD","label":"Area","mean_abs_shap":0.083886,"mean_signed_shap":-0.004881},{"feature":"img_emb_022","modality":"IMAGE","label":"Image embedding 022","mean_abs_shap":0.078957,"mean_signed_shap":-0.005424},{"feature":"img_emb_017","modality":"IMAGE","label":"Image embedding 017","mean_abs_shap":0.077356,"mean_signed_shap":-0.003757},{"feature":"pcd_NDBI","modality":"PCD","label":"NDBI (Built-up)","mean_abs_shap":0.074163,"mean_signed_shap":-0.003869},{"feature":"img_emb_019","modality":"IMAGE","label":"Image embedding 019","mean_abs_shap":0.072267,"mean_signed_shap":0.001057},{"feature":"img_emb_018","modality":"IMAGE","label":"Image embedding 018","mean_abs_shap":0.072244,"mean_signed_shap":-0.004373},{"feature":"img_emb_020","modality":"IMAGE","label":"Image embedding 020","mean_abs_shap":0.071392,"mean_signed_shap":0.001817},{"feature":"img_emb_011","modality":"IMAGE","label":"Image embedding 011","mean_abs_shap":0.070153,"mean_signed_shap":-0.006581},{"feature":"img_emb_031","modality":"IMAGE","label":"Image embedding 031","mean_abs_shap":0.070145,"mean_signed_shap":-0.003511},{"feature":"nlp_freq_Investasi_Industri","modality":"NLP","label":"NLP: Investasi Industri","mean_abs_shap":0.068745,"mean_signed_shap":0.019247},{"feature":"pcd_NTL","modality":"PCD","label":"Night-time Light","mean_abs_shap":0.065209,"mean_signed_shap":-0.000234},{"feature":"img_emb_015","modality":"IMAGE","label":"Image embedding 015","mean_abs_shap":0.064361,"mean_signed_shap":-0.00427},{"feature":"img_emb_021","modality":"IMAGE","label":"Image embedding 021","mean_abs_shap":0.06319,"mean_signed_shap":-0.002941},{"feature":"pcd_jumlah_poi","modality":"PCD","label":"POI Count","mean_abs_shap":0.058885,"mean_signed_shap":-0.006337},{"feature":"img_emb_000","modality":"IMAGE","label":"Image embedding 000","mean_abs_shap":0.055505,"mean_signed_shap":-0.003466},{"feature":"pcd_luas_bangunan_otsu_km2","modality":"PCD","label":"Built Area Otsu","mean_abs_shap":0.053665,"mean_signed_shap":-0.00332},{"feature":"nlp_freq_Bencana_Kerentanan","modality":"NLP","label":"NLP: Bencana Kerentanan","mean_abs_shap":0.051688,"mean_signed_shap":0.00408},{"feature":"img_emb_009","modality":"IMAGE","label":"Image embedding 009","mean_abs_shap":0.051115,"mean_signed_shap":0.001609},{"feature":"img_emb_007","modality":"IMAGE","label":"Image embedding 007","mean_abs_shap":0.050115,"mean_signed_shap":0.00074},{"feature":"nlp_freq_Konflik_Kriminalitas_Sosial","modality":"NLP","label":"NLP: Konflik Kriminalitas Sosial","mean_abs_shap":0.044838,"mean_signed_shap":0.004652},{"feature":"img_emb_014","modality":"IMAGE","label":"Image embedding 014","mean_abs_shap":0.044341,"mean_signed_shap":0.001438},{"feature":"pcd_permukiman","modality":"PCD","label":"Settlement","mean_abs_shap":0.044128,"mean_signed_shap":-0.004324},{"feature":"img_emb_027","modality":"IMAGE","label":"Image embedding 027","mean_abs_shap":0.04388,"mean_signed_shap":0.000523},{"feature":"nlp_freq_Ketenagakerjaan","modality":"NLP","label":"NLP: Ketenagakerjaan","mean_abs_shap":0.043645,"mean_signed_shap":0.00912},{"feature":"pcd_density","modality":"PCD","label":"Density","mean_abs_shap":0.042851,"mean_signed_shap":-0.002287},{"feature":"img_emb_001","modality":"IMAGE","label":"Image embedding 001","mean_abs_shap":0.042697,"mean_signed_shap":-0.001371},{"feature":"img_emb_012","modality":"IMAGE","label":"Image embedding 012","mean_abs_shap":0.041597,"mean_signed_shap":-0.001326},{"feature":"img_emb_008","modality":"IMAGE","label":"Image embedding 008","mean_abs_shap":0.041454,"mean_signed_shap":0.004906},{"feature":"nlp_freq_Perumahan_Sanitasi","modality":"NLP","label":"NLP: Perumahan Sanitasi","mean_abs_shap":0.041346,"mean_signed_shap":0.012346},{"feature":"nlp_freq_Infrastruktur_Akses","modality":"NLP","label":"NLP: Infrastruktur Akses","mean_abs_shap":0.041193,"mean_signed_shap":0.005345},{"feature":"img_emb_005","modality":"IMAGE","label":"Image embedding 005","mean_abs_shap":0.040976,"mean_signed_shap":-0.00178},{"feature":"pcd_VANUI","modality":"PCD","label":"VANUI","mean_abs_shap":0.038839,"mean_signed_shap":0.001666}]}